rtl/bayer_to_rgb.v
module bayer_to_rgb (
    input  wire        clk,
    input  wire        rst_n,
    input  wire [7:0]  pixel_in,
    input  wire [9:0]  x,
    input  wire [9:0]  y,

    output reg [7:0]   r,
    output reg [7:0]   g,
    output reg [7:0]   b
);

always @(posedge clk or negedge rst_n) begin

    if (!rst_n) begin
        r <= 0;
        g <= 0;
        b <= 0;
    end

    else begin

        r <= 0;
        g <= 0;
        b <= 0;

        // RGGB Bayer pattern

        if ((y % 2 == 0) && (x % 2 == 0)) begin
            // Red pixel
            r <= pixel_in;
        end

        else if ((y % 2 == 0) && (x % 2 == 1)) begin
            // Green pixel
            g <= pixel_in;
        end

        else if ((y % 2 == 1) && (x % 2 == 0)) begin
            // Green pixel
            g <= pixel_in;
        end

        else begin
            // Blue pixel
            b <= pixel_in;
        end

    end

end

endmodule

tb/bayer_to_rgb_tb.v
`timescale 1ns / 1ps

module bayer_to_rgb_tb;

    reg clk;
    reg rst_n;

    reg [7:0] pixel_in;
    reg [9:0] x;
    reg [9:0] y;

    wire [7:0] r;
    wire [7:0] g;
    wire [7:0] b;

    bayer_to_rgb uut (
        .clk(clk),
        .rst_n(rst_n),
        .pixel_in(pixel_in),
        .x(x),
        .y(y),
        .r(r),
        .g(g),
        .b(b)
    );

    always #5 clk = ~clk;

    initial begin
        $dumpfile("sim/bayer_to_rgb.vcd");
        $dumpvars(0, bayer_to_rgb_tb);
        
        clk = 0;
        rst_n = 0;

        pixel_in = 0;
        x = 0;
        y = 0;

        #20;
        rst_n = 1;

        // Red pixel
        #10;
        x = 0;
        y = 0;
        pixel_in = 8'hFF;

        // Green pixel
        #10;
        x = 1;
        y = 0;
        pixel_in = 8'hAA;

        // Green pixel
        #10;
        x = 0;
        y = 1;
        pixel_in = 8'h55;

        // Blue pixel
        #10;
        x = 1;
        y = 1;
        pixel_in = 8'h11;

        #50;

        $finish;

    end

endmodule

sim/bayer_to_rgb.vcd
$date
	Sun May 31 14:16:39 2026
$end
$version
	Icarus Verilog
$end
$timescale
	1ps
$end
$scope module bayer_to_rgb_tb $end
$var wire 8 ! r [7:0] $end
$var wire 8 " g [7:0] $end
$var wire 8 # b [7:0] $end
$var reg 1 $ clk $end
$var reg 8 % pixel_in [7:0] $end
$var reg 1 & rst_n $end
$var reg 10 ' x [9:0] $end
$var reg 10 ( y [9:0] $end
$scope module uut $end
$var wire 1 $ clk $end
$var wire 8 ) pixel_in [7:0] $end
$var wire 1 & rst_n $end
$var wire 10 * x [9:0] $end
$var wire 10 + y [9:0] $end
$var reg 8 , b [7:0] $end
$var reg 8 - g [7:0] $end
$var reg 8 . r [7:0] $end
$upscope $end
$upscope $end
$enddefinitions $end
$comment Show the parameter values. $end
$dumpall
$end
#0
$dumpvars
b0 .
b0 -
b0 ,
b0 +
b0 *
b0 )
b0 (
b0 '
0&
b0 %
0$
b0 #
b0 "
b0 !
$end
#5000
1$
#10000
0$
#15000
1$
#20000
0$
1&
#25000
1$
#30000
0$
b11111111 %
b11111111 )
#35000
b11111111 !
b11111111 .
1$
#40000
0$
b10101010 %
b10101010 )
b1 '
b1 *
#45000
b10101010 "
b10101010 -
b0 !
b0 .
1$
#50000
0$
b1010101 %
b1010101 )
b1 (
b1 +
b0 '
b0 *
#55000
b1010101 "
b1010101 -
1$
#60000
0$
b10001 %
b10001 )
b1 '
b1 *
#65000
b10001 #
b10001 ,
b0 "
b0 -
1$
#70000
0$
#75000
b10001 #
b10001 ,
1$
#80000
0$
#85000
b10001 #
b10001 ,
1$
#90000
0$
#95000
b10001 #
b10001 ,
1$
#100000
0$
#105000
b10001 #
b10001 ,
1$
