rtl/bayer_to_rgb.v
module bayer_to_rgb (
    input  wire        clk,
    input  wire        rst_n,
    input wire valid_in,
    input  wire [7:0]  pixel_in,
    input  wire [9:0]  x,
    input  wire [9:0]  y,

    output reg [7:0]   r,
    output reg [7:0]   g,
    output reg [7:0]   b
);

always @(posedge clk or negedge rst_n) begin

    if (!rst_n) begin
        r <= 0;
        g <= 0;
        b <= 0;
    end

    else begin

        r <= 0;
        g <= 0;
        b <= 0;

        // RGGB Bayer pattern
        if (valid_in) begin
            if ((y % 2 == 0) && (x % 2 == 0)) begin
            // Red pixel
                 r <= pixel_in;
            end

            else if ((y % 2 == 0) && (x % 2 == 1)) begin
                 // Green pixel
                   g <= pixel_in;
            end

             else if ((y % 2 == 1) && (x % 2 == 0)) begin
                  // Green pixel
                  g <= pixel_in;
            end

             else begin
                 // Blue pixel
                  b <= pixel_in;
             end

         end

    end
end

endmodule

rtl/ov7670_capture.v
// ov7670_capture.v
// Captures raw 8-bit Bayer pixels from the OV7670 camera sensor.
// All logic runs in the pclk (pixel clock) domain (~24 MHz on hardware).
//
// OV7670 Signal Reference:
//   pclk      - Pixel clock from camera. Every rising edge delivers one byte of data.
//   vsync     - Vertical sync. HIGH during the blanking gap BETWEEN frames.
//               LOW while a frame is actively being transmitted.
//   href      - Horizontal reference. HIGH while a row of pixels is being sent.
//               LOW during horizontal blanking between rows.
//   cam_data  - Raw 8-bit Bayer byte from the camera. Valid on each pclk when href is HIGH.

module ov7670_capture (
    input  wire       pclk,        // Pixel clock from OV7670 (~24 MHz)
    input  wire       rst_n,       // Active-low asynchronous reset
    input  wire       vsync,       // Vertical sync (HIGH = blanking, LOW = active frame)
    input  wire       href,        // Horizontal reference (HIGH = active row)
    input  wire [7:0] cam_data,    // Raw Bayer pixel byte from camera
    output reg  [7:0] pixel_data,  // Captured pixel byte (holds last value when invalid)
    output reg        pixel_valid, // HIGH for one pclk cycle per valid pixel byte
    output reg        frame_valid, // HIGH while a frame is actively being sent
    output reg        line_valid   // HIGH while a row of pixels is being sent
);

    // All outputs are registered on posedge pclk.
    // Registering outputs removes glitches and ensures clean, synchronous
    // transitions that downstream modules can safely sample.
    //
    // Async reset (negedge rst_n) brings all outputs to a known safe state
    // without waiting for a clock edge — useful during power-up.

    always @(posedge pclk or negedge rst_n) begin
        if (!rst_n) begin
            // Reset all outputs to 0 (safe/inactive state)
            pixel_data  <= 8'h00;
            pixel_valid <= 1'b0;
            frame_valid <= 1'b0;
            line_valid  <= 1'b0;
        end else begin
            // vsync is HIGH during blanking (no frame), LOW during active frame.
            // We invert it so frame_valid=1 means "a frame is in progress" —
            // a more intuitive polarity for downstream logic.
            frame_valid <= ~vsync;

            // line_valid directly follows href: HIGH when a row is being sent.
            line_valid  <= href;

            if (href) begin
                // Camera is sending valid pixel data this clock cycle.
                // Latch the byte and assert pixel_valid for exactly one cycle.
                pixel_data  <= cam_data;
                pixel_valid <= 1'b1;
            end else begin
                // No active row — deassert pixel_valid.
                // pixel_data retains its last value (don't-care but harmless).
                pixel_valid <= 1'b0;
            end
        end
    end

endmodule

rtl/camera_pipeline_top.v
// camera_pipeline_top.v
//
// Camera Pipeline:
//   OV7670 camera signals (pclk domain)
//       -> ov7670_capture: generates pixel_data/pixel_valid/frame_valid/line_valid
//       -> pixel coordinate counter: tracks x/y position in frame
//       -> bayer_to_rgb ISP: converts raw Bayer bytes to RGB
//
// All logic runs on pclk (the camera's own pixel clock, ~24 MHz on hardware).
// This is a simulation-architecture stub — no CDC (clock domain crossing)
// logic is needed because there is only one clock domain here.

module camera_pipeline_top (
    input  wire       pclk,      // camera pixel clock (everything runs on this)
    input  wire       rst_n,     // active-low asynchronous reset
    input  wire       vsync,     // from camera: HIGH = vertical blanking between frames
    input  wire       href,      // from camera: HIGH = active pixel row
    input  wire [7:0] cam_data,  // raw Bayer bytes from OV7670 sensor
    output wire [7:0] r,         // red channel out from ISP
    output wire [7:0] g,         // green channel out from ISP
    output wire [7:0] b,         // blue channel out from ISP
    output wire       isp_valid  // HIGH when r/g/b hold a valid decoded pixel
);

    // -----------------------------------------------------------------------
    // Stage 1 — OV7670 capture
    // Converts the raw camera handshake signals (vsync/href/cam_data) into
    // a clean synchronous pixel stream with validity flags.
    // -----------------------------------------------------------------------

    wire [7:0] pixel_data;   // latched raw Bayer byte from capture block
    wire       pixel_valid;  // pulses HIGH for exactly one pclk per captured byte
    wire       frame_valid;  // HIGH while a frame is being transmitted
    wire       line_valid;   // HIGH while a row of pixels is being transmitted

    ov7670_capture u_capture (
        .pclk        (pclk),
        .rst_n       (rst_n),
        .vsync       (vsync),
        .href        (href),
        .cam_data    (cam_data),
        .pixel_data  (pixel_data),
        .pixel_valid (pixel_valid),
        .frame_valid (frame_valid),
        .line_valid  (line_valid)
    );

    // -----------------------------------------------------------------------
    // Stage 2 — Pixel coordinate counter
    // Tracks the (x, y) address of every pixel within the current frame.
    //
    // Reset / frame boundary: when rst_n goes low OR frame_valid falls
    //   low, reset both counters to 0.
    // End of row: when line_valid falls low (prev=1, now=0), increment y
    //   and reset x.
    // Each pixel: when pixel_valid is high, increment x.
    //
    // NOTE: ov7670_capture registers its outputs, so we use the registered
    // values of frame_valid and line_valid for edge detection.
    // -----------------------------------------------------------------------

    reg [9:0] pixel_x;          // current column (0-based)
    reg [9:0] pixel_y;          // current row    (0-based)

    reg prev_frame_valid;       // previous cycle's frame_valid (for negedge detect)
    reg prev_line_valid;        // previous cycle's line_valid  (for negedge detect)

    always @(posedge pclk or negedge rst_n) begin
        if (!rst_n) begin
            // Asynchronous reset — put counters and shadow regs to known state
            pixel_x          <= 10'd0;
            pixel_y          <= 10'd0;
            prev_frame_valid <= 1'b0;
            prev_line_valid  <= 1'b0;
        end else begin
            // Update shadow registers every cycle so we can detect falling edges
            prev_frame_valid <= frame_valid;
            prev_line_valid  <= line_valid;

            // --- Frame boundary ---
            // frame_valid just fell (1->0): a frame ended, reset to origin
            if (prev_frame_valid && !frame_valid) begin
                pixel_x <= 10'd0;
                pixel_y <= 10'd0;

            // --- Row boundary ---
            // line_valid just fell (1->0): a row ended, move to next row
            end else if (prev_line_valid && !line_valid) begin
                pixel_y <= pixel_y + 10'd1;
                pixel_x <= 10'd0;

            // --- Pixel advance ---
            // pixel_valid pulses once per captured byte
            end else if (pixel_valid) begin
                pixel_x <= pixel_x + 10'd1;
            end
        end
    end

    // -----------------------------------------------------------------------
    // Stage 3 — Bayer-to-RGB ISP
    // Decodes each raw Bayer byte into an (R, G, B) triple using the RGGB
    // Bayer pattern.  The clock port in bayer_to_rgb is named "clk" — we
    // connect our pclk to it because everything runs in the same domain.
    // -----------------------------------------------------------------------

    bayer_to_rgb u_isp (
        .clk      (pclk),        // bayer_to_rgb's port is named "clk"; driven by pclk
        .rst_n    (rst_n),
        .valid_in (pixel_valid), // assert when a fresh pixel byte has arrived
        .pixel_in (pixel_data),  // raw Bayer byte from capture stage
        .x        (pixel_x),     // column address tracked above
        .y        (pixel_y),     // row address tracked above
        .r        (r),
        .g        (g),
        .b        (b)
    );

    // -----------------------------------------------------------------------
    // isp_valid: pass pixel_valid straight through.
    // The ISP registers its outputs, so r/g/b will be valid on the NEXT
    // cycle after pixel_valid.  For a simulation stub this is a useful
    // "a pixel was processed this cycle" indicator.
    // -----------------------------------------------------------------------
    assign isp_valid = pixel_valid;

endmodule

tb/camera_pipeline_top_tb.v
`timescale 1ns / 1ps
// camera_pipeline_top_tb.v
//
// Testbench for camera_pipeline_top.
// Simulates a tiny 4x4 Bayer frame being delivered by the OV7670 interface,
// then checks that isp_valid fires and RGB output is produced.

module camera_pipeline_top_tb;

    // -----------------------------------------------------------------------
    // DUT signal declarations
    // -----------------------------------------------------------------------
    reg        pclk;
    reg        rst_n;
    reg        vsync;
    reg        href;
    reg  [7:0] cam_data;

    wire [7:0] r;
    wire [7:0] g;
    wire [7:0] b;
    wire       isp_valid;

    // -----------------------------------------------------------------------
    // Instantiate the design under test
    // -----------------------------------------------------------------------
    camera_pipeline_top uut (
        .pclk     (pclk),
        .rst_n    (rst_n),
        .vsync    (vsync),
        .href     (href),
        .cam_data (cam_data),
        .r        (r),
        .g        (g),
        .b        (b),
        .isp_valid(isp_valid)
    );

    // -----------------------------------------------------------------------
    // Clock: 10 ns period (100 MHz — fast enough to stress the logic cleanly)
    // -----------------------------------------------------------------------
    initial pclk = 0;
    always #5 pclk = ~pclk;

    // -----------------------------------------------------------------------
    // VCD waveform dump for GTKWave inspection
    // -----------------------------------------------------------------------
    initial begin
        $dumpfile("sim/camera_pipeline_top.vcd");
        $dumpvars(0, camera_pipeline_top_tb);
    end

    // -----------------------------------------------------------------------
    // Observation latches
    // Record whether isp_valid ever fired, and the last RGB value seen.
    // -----------------------------------------------------------------------
    reg        isp_valid_seen;
    reg  [7:0] last_r, last_g, last_b;

    initial begin
        isp_valid_seen = 0;
        last_r = 0;
        last_g = 0;
        last_b = 0;
    end

    always @(posedge pclk) begin
        if (isp_valid) begin
            isp_valid_seen <= 1;
            last_r <= r;
            last_g <= g;
            last_b <= b;
            $display("[%0t] isp_valid: r=%0d g=%0d b=%0d", $time, r, g, b);
        end
    end

    // -----------------------------------------------------------------------
    // Loop variables (must be declared at module scope for Verilog-2001)
    // -----------------------------------------------------------------------
    integer row;
    integer col;

    // -----------------------------------------------------------------------
    // Main stimulus
    // -----------------------------------------------------------------------
    initial begin

        // --- 1. Initialise and hold in reset ---
        rst_n    = 0;
        vsync    = 1;   // HIGH = blanking (no frame in progress)
        href     = 0;
        cam_data = 8'h00;
        #20;            // hold reset for 2 clock periods

        // --- 2. Release reset ---
        rst_n = 1;
        #30;            // a few cycles of blanking while the camera "warms up"

        // --- 3. Start a frame: pull vsync LOW ---
        vsync = 0;      // LOW = active frame
        #10;

        // --- 4. Drive a 4-row x 4-column Bayer frame ---
        // cam_data value = row*16 + col  (gives easy-to-spot patterns in waveform)
        for (row = 0; row < 4; row = row + 1) begin
            href = 1;                           // row active
            for (col = 0; col < 4; col = col + 1) begin
                cam_data = (row * 16 + col);    // unique value per pixel
                #10;                            // one clock period per byte
            end
            href = 0;                           // end of row (horizontal blanking)
            #20;                                // brief inter-row gap
        end

        // --- 5. End of frame: pull vsync HIGH again ---
        vsync = 1;
        #40;

        // -----------------------------------------------------------------------
        // PASS / FAIL report
        // -----------------------------------------------------------------------
        if (isp_valid_seen)
            $display("PASS: isp_valid was asserted during the frame (isp_valid_seen=1)");
        else
            $display("FAIL: isp_valid was never asserted (isp_valid_seen=0)");

        $display("Last RGB output: r=%0d g=%0d b=%0d", last_r, last_g, last_b);

        $finish;
    end

endmodule

sim/camera_pipeline_top.vcd
$date
	Tue Jun 02 14:21:52 2026
$end
$version
	Icarus Verilog
$end
$timescale
	1ps
$end
$scope module camera_pipeline_top_tb $end
$var wire 8 ! r [7:0] $end
$var wire 1 " isp_valid $end
$var wire 8 # g [7:0] $end
$var wire 8 $ b [7:0] $end
$var reg 8 % cam_data [7:0] $end
$var reg 1 & href $end
$var reg 1 ' isp_valid_seen $end
$var reg 8 ( last_b [7:0] $end
$var reg 8 ) last_g [7:0] $end
$var reg 8 * last_r [7:0] $end
$var reg 1 + pclk $end
$var reg 1 , rst_n $end
$var reg 1 - vsync $end
$var integer 32 . col [31:0] $end
$var integer 32 / row [31:0] $end
$scope module uut $end
$var wire 8 0 cam_data [7:0] $end
$var wire 1 & href $end
$var wire 1 " isp_valid $end
$var wire 1 + pclk $end
$var wire 1 , rst_n $end
$var wire 1 - vsync $end
$var wire 8 1 r [7:0] $end
$var wire 1 2 pixel_valid $end
$var wire 8 3 pixel_data [7:0] $end
$var wire 1 4 line_valid $end
$var wire 8 5 g [7:0] $end
$var wire 1 6 frame_valid $end
$var wire 8 7 b [7:0] $end
$var reg 10 8 pixel_x [9:0] $end
$var reg 10 9 pixel_y [9:0] $end
$var reg 1 : prev_frame_valid $end
$var reg 1 ; prev_line_valid $end
$scope module u_capture $end
$var wire 8 < cam_data [7:0] $end
$var wire 1 & href $end
$var wire 1 + pclk $end
$var wire 1 , rst_n $end
$var wire 1 - vsync $end
$var reg 1 6 frame_valid $end
$var reg 1 4 line_valid $end
$var reg 8 = pixel_data [7:0] $end
$var reg 1 2 pixel_valid $end
$upscope $end
$scope module u_isp $end
$var wire 1 + clk $end
$var wire 8 > pixel_in [7:0] $end
$var wire 1 , rst_n $end
$var wire 1 2 valid_in $end
$var wire 10 ? x [9:0] $end
$var wire 10 @ y [9:0] $end
$var reg 8 A b [7:0] $end
$var reg 8 B g [7:0] $end
$var reg 8 C r [7:0] $end
$upscope $end
$upscope $end
$upscope $end
$enddefinitions $end
$comment Show the parameter values. $end
$dumpall
$end
#0
$dumpvars
b0 C
b0 B
b0 A
b0 @
b0 ?
b0 >
b0 =
b0 <
0;
0:
b0 9
b0 8
b0 7
06
b0 5
04
b0 3
02
b0 1
b0 0
bx /
bx .
1-
0,
0+
b0 *
b0 )
b0 (
0'
0&
b0 %
b0 $
b0 #
0"
b0 !
$end
#5000
1+
#10000
0+
#15000
1+
#20000
0+
1,
#25000
1+
#30000
0+
#35000
1+
#40000
0+
#45000
1+
#50000
0+
0-
#55000
16
1+
#60000
0+
b0 .
1&
b0 /
#65000
1:
1"
12
14
1+
#70000
0+
b1 %
b1 0
b1 <
b1 .
#75000
b1 3
b1 =
b1 >
b1 8
b1 ?
1;
1'
1+
#80000
0+
b10 %
b10 0
b10 <
b10 .
#85000
b10 8
b10 ?
b1 #
b1 5
b1 B
b10 3
b10 =
b10 >
1+
#90000
0+
b11 %
b11 0
b11 <
b11 .
#95000
b11 3
b11 =
b11 >
b10 !
b10 1
b10 C
b0 #
b0 5
b0 B
b11 8
b11 ?
b1 )
1+
#100000
0+
0&
b100 .
#105000
b100 8
b100 ?
b11 #
b11 5
b11 B
b0 !
b0 1
b0 C
0"
02
04
b0 )
b10 *
1+
#110000
0+
#115000
b0 #
b0 5
b0 B
b0 8
b0 ?
b1 9
b1 @
0;
1+
#120000
0+
b10000 %
b10000 0
b10000 <
b0 .
1&
b1 /
#125000
1"
12
b10000 3
b10000 =
b10000 >
14
1+
#130000
0+
b10001 %
b10001 0
b10001 <
b1 .
#135000
b10001 3
b10001 =
b10001 >
b10000 #
b10000 5
b10000 B
b1 8
b1 ?
1;
b0 *
1+
#140000
0+
b10010 %
b10010 0
b10010 <
b10 .
#145000
b10 8
b10 ?
b10001 $
b10001 7
b10001 A
b0 #
b0 5
b0 B
b10010 3
b10010 =
b10010 >
b10000 )
1+
#150000
0+
b10011 %
b10011 0
b10011 <
b11 .
#155000
b10011 3
b10011 =
b10011 >
b10010 #
b10010 5
b10010 B
b0 $
b0 7
b0 A
b11 8
b11 ?
b10001 (
b0 )
1+
#160000
0+
0&
b100 .
#165000
b100 8
b100 ?
b10011 $
b10011 7
b10011 A
b0 #
b0 5
b0 B
0"
02
04
b0 (
b10010 )
1+
#170000
0+
#175000
b0 $
b0 7
b0 A
b0 8
b0 ?
b10 9
b10 @
0;
1+
#180000
0+
b100000 %
b100000 0
b100000 <
b0 .
1&
b10 /
#185000
1"
12
b100000 3
b100000 =
b100000 >
14
1+
#190000
0+
b100001 %
b100001 0
b100001 <
b1 .
#195000
b100001 3
b100001 =
b100001 >
b100000 !
b100000 1
b100000 C
b1 8
b1 ?
1;
b0 )
1+
#200000
0+
b100010 %
b100010 0
b100010 <
b10 .
#205000
b10 8
b10 ?
b100001 #
b100001 5
b100001 B
b0 !
b0 1
b0 C
b100010 3
b100010 =
b100010 >
b100000 *
1+
#210000
0+
b100011 %
b100011 0
b100011 <
b11 .
#215000
b100011 3
b100011 =
b100011 >
b100010 !
b100010 1
b100010 C
b0 #
b0 5
b0 B
b11 8
b11 ?
b100001 )
b0 *
1+
#220000
0+
0&
b100 .
#225000
b100 8
b100 ?
b100011 #
b100011 5
b100011 B
b0 !
b0 1
b0 C
0"
02
04
b0 )
b100010 *
1+
#230000
0+
#235000
b0 #
b0 5
b0 B
b0 8
b0 ?
b11 9
b11 @
0;
1+
#240000
0+
b110000 %
b110000 0
b110000 <
b0 .
1&
b11 /
#245000
1"
12
b110000 3
b110000 =
b110000 >
14
1+
#250000
0+
b110001 %
b110001 0
b110001 <
b1 .
#255000
b110001 3
b110001 =
b110001 >
b110000 #
b110000 5
b110000 B
b1 8
b1 ?
1;
b0 *
1+
#260000
0+
b110010 %
b110010 0
b110010 <
b10 .
#265000
b10 8
b10 ?
b110001 $
b110001 7
b110001 A
b0 #
b0 5
b0 B
b110010 3
b110010 =
b110010 >
b110000 )
1+
#270000
0+
b110011 %
b110011 0
b110011 <
b11 .
#275000
b110011 3
b110011 =
b110011 >
b110010 #
b110010 5
b110010 B
b0 $
b0 7
b0 A
b11 8
b11 ?
b110001 (
b0 )
1+
#280000
0+
0&
b100 .
#285000
b100 8
b100 ?
b110011 $
b110011 7
b110011 A
b0 #
b0 5
b0 B
0"
02
04
b0 (
b110010 )
1+
#290000
0+
#295000
b0 $
b0 7
b0 A
b0 8
b0 ?
b100 9
b100 @
0;
1+
#300000
0+
1-
b100 /
#305000
06
1+
#310000
0+
#315000
b0 9
b0 @
0:
1+
