rtl/fifo_reader.v
// fifo_reader.v
// ---------------------------------------------------------------------------
// Models the FPGA-side logic for reading pixels from an external FIFO chip
// (e.g. AL422B used on OV7670+FIFO camera modules).
//
// HOW IT WORKS:
//   The camera continuously writes pixels into the FIFO.  This module reads
//   them out at the FPGA's own pace using a separate read clock (rclk).
//
// TIMING (1-cycle data latency):
//   Cycle N  : fifo_empty=0 → fifo_rd_en asserted HIGH
//   Cycle N+1: FIFO chip places the byte on fifo_data; data_latched=1
//              → pixel_out captures fifo_data, pixel_valid pulses HIGH
//   Cycle N+2: next byte is in flight (or fifo_rd_en de-asserts if empty)
// ---------------------------------------------------------------------------

module fifo_reader (
    input  wire       rclk,        // FPGA-side read clock (independent of camera pclk)
    input  wire       rst_n,       // Active-low asynchronous reset
    input  wire       fifo_empty,  // HIGH when FIFO contains no more bytes
    input  wire [7:0] fifo_data,   // Byte output from FIFO (valid ONE cycle after rd_en)
    output reg        fifo_rd_en,  // Assert HIGH to advance FIFO read pointer by one byte
    output reg  [7:0] pixel_out,   // Captured pixel byte (valid when pixel_valid=1)
    output reg        pixel_valid  // HIGH for exactly one rclk cycle when pixel_out is ready
);

    // data_latched: delayed copy of fifo_rd_en.
    // Because the FIFO chip needs one clock cycle to place data on fifo_data
    // after rd_en is asserted, we use this register to know when fifo_data
    // actually holds a valid byte.
    reg data_latched;

    always @(posedge rclk or negedge rst_n) begin
        if (!rst_n) begin
            // Reset all outputs and internal state to known values
            fifo_rd_en   <= 1'b0;
            pixel_out    <= 8'h00;
            pixel_valid  <= 1'b0;
            data_latched <= 1'b0;
        end else begin

            // ----------------------------------------------------------------
            // Step 1: Drive the FIFO read-enable.
            //   Assert rd_en whenever the FIFO is not empty so we keep reading
            //   back-to-back bytes.  De-assert as soon as fifo_empty goes HIGH
            //   to stop advancing the pointer.
            // ----------------------------------------------------------------
            fifo_rd_en <= ~fifo_empty;

            // ----------------------------------------------------------------
            // Step 2: Track when data will be ready.
            //   data_latched captures whether rd_en was asserted AND the FIFO
            //   was not empty this cycle — meaning a byte was actually sent out
            //   by the FIFO chip and will appear on fifo_data next cycle.
            //
            //   We AND with ~fifo_empty so that if the FIFO becomes empty on
            //   the same cycle rd_en is high (last byte just consumed), we do
            //   NOT set data_latched — preventing a spurious pixel_valid pulse
            //   one cycle after the FIFO runs out.
            // ----------------------------------------------------------------
            data_latched <= fifo_rd_en & ~fifo_empty;

            // ----------------------------------------------------------------
            // Step 3: Capture the byte and signal the downstream logic.
            //   Only latch fifo_data and assert pixel_valid when data_latched
            //   tells us the FIFO output is stable.
            // ----------------------------------------------------------------
            if (data_latched) begin
                pixel_out   <= fifo_data;   // capture the valid byte
                pixel_valid <= 1'b1;        // tell downstream: data is ready
            end else begin
                pixel_valid <= 1'b0;        // no valid data this cycle
                // pixel_out retains its last value (don't care when valid=0)
            end

        end
    end

endmodule

tb/fifo_reader_tb.v
// fifo_reader_tb.v
// ---------------------------------------------------------------------------
// Testbench for fifo_reader.v
//
// Simulates an 8-byte behavioral FIFO pre-loaded with a test pattern.
// The testbench lets the fifo_reader drain all 8 bytes, then checks that
// every pixel arrived in the correct order.
// ---------------------------------------------------------------------------

`timescale 1ns / 1ps

module fifo_reader_tb;

    // -----------------------------------------------------------------------
    // DUT signal declarations
    // -----------------------------------------------------------------------
    reg        rclk;         // FPGA read clock
    reg        rst_n;        // active-low reset
    wire       fifo_empty_wire; // driven by behavioral FIFO
    wire [7:0] fifo_data_wire;  // driven by behavioral FIFO
    wire       fifo_rd_en;   // driven by DUT
    wire [7:0] pixel_out;    // DUT output
    wire       pixel_valid;  // DUT output

    // -----------------------------------------------------------------------
    // Instantiate the DUT
    // -----------------------------------------------------------------------
    fifo_reader uut (
        .rclk        (rclk),
        .rst_n       (rst_n),
        .fifo_empty  (fifo_empty_wire),
        .fifo_data   (fifo_data_wire),
        .fifo_rd_en  (fifo_rd_en),
        .pixel_out   (pixel_out),
        .pixel_valid (pixel_valid)
    );

    // -----------------------------------------------------------------------
    // Behavioral FIFO model
    // 8-byte memory pre-loaded with a known test pattern.
    //
    // This models a registered-output FIFO (like the AL422B):
    //   - fifo_data_wire is a REGISTERED output, not a combinatorial read.
    //   - When rd_en is asserted, the CURRENT byte (at the current pointer)
    //     is captured into fifo_data_reg on that clock edge, and the pointer
    //     advances so the next rd_en reads the next byte.
    //   - One cycle later, fifo_data_reg holds the correct byte — this lines
    //     up exactly with data_latched in the DUT.
    // -----------------------------------------------------------------------
    reg [7:0] fifo_mem [0:7]; // 8-byte FIFO storage
    reg [3:0] fifo_rd_ptr;    // points to the next byte to be read
    integer   fifo_count;     // number of bytes remaining in FIFO
    reg [7:0] fifo_data_reg;  // registered output: holds byte captured on last rd_en

    // Data bus is the registered output (valid one cycle after rd_en)
    assign fifo_data_wire  = fifo_data_reg;
    // Empty flag goes HIGH when no bytes remain
    assign fifo_empty_wire = (fifo_count == 0);

    // Load test pattern and initialise pointers
    initial begin
        fifo_mem[0] = 8'hC0; fifo_mem[1] = 8'hC1;
        fifo_mem[2] = 8'hC2; fifo_mem[3] = 8'hC3;
        fifo_mem[4] = 8'hD0; fifo_mem[5] = 8'hD1;
        fifo_mem[6] = 8'hD2; fifo_mem[7] = 8'hD3;
        fifo_rd_ptr  = 0;
        fifo_count   = 8;
        fifo_data_reg = 8'hXX; // undefined until first read
    end

    // On rd_en: capture current byte into output register, then advance pointer.
    // This is the key: fifo_data_reg gets fifo_mem[current_ptr] BEFORE the
    // pointer increments, so the DUT sees the correct byte one cycle later.
    always @(posedge rclk) begin
        if (fifo_rd_en && fifo_count > 0) begin
            fifo_data_reg <= fifo_mem[fifo_rd_ptr]; // capture byte for output
            fifo_rd_ptr   <= fifo_rd_ptr + 1;       // advance to next byte
            fifo_count    <= fifo_count  - 1;       // one fewer byte available
        end
    end

    // -----------------------------------------------------------------------
    // Clock generator: 10 ns period (100 MHz)
    // -----------------------------------------------------------------------
    initial rclk = 0;
    always #5 rclk = ~rclk;

    // -----------------------------------------------------------------------
    // Checker state
    // -----------------------------------------------------------------------
    // Expected byte sequence matches the FIFO load order
    reg [7:0] expected [0:7];
    integer pixel_count; // counts pixel_valid pulses received
    integer errors;      // counts value mismatches
    reg     all_ok;      // set to 0 if any mismatch is detected

    initial begin
        expected[0] = 8'hC0; expected[1] = 8'hC1;
        expected[2] = 8'hC2; expected[3] = 8'hC3;
        expected[4] = 8'hD0; expected[5] = 8'hD1;
        expected[6] = 8'hD2; expected[7] = 8'hD3;
        pixel_count = 0;
        errors      = 0;
        all_ok      = 1;
    end

    // On every rising edge, check pixel_valid and compare to expected value
    always @(posedge rclk) begin
        if (pixel_valid) begin
            $display("[%0t ns] pixel_valid=1  pixel_out=0x%02X  (expected 0x%02X)",
                     $time, pixel_out, expected[pixel_count]);

            if (pixel_out !== expected[pixel_count]) begin
                $display("  *** MISMATCH at index %0d: got 0x%02X, expected 0x%02X ***",
                         pixel_count, pixel_out, expected[pixel_count]);
                errors  = errors + 1;
                all_ok  = 0;
            end
            pixel_count = pixel_count + 1;
        end
    end

    // -----------------------------------------------------------------------
    // Main stimulus
    // -----------------------------------------------------------------------
    initial begin
        // Set up waveform dump
        $dumpfile("sim/fifo_reader.vcd");
        $dumpvars(0, fifo_reader_tb);

        // 1. Assert reset
        rst_n = 0;
        #20;           // hold reset for 2 clock cycles

        // 2. Release reset and let the reader drain the FIFO
        rst_n = 1;

        // Wait long enough for all 8 bytes to be read and their pixel_valid
        // pulses to arrive.  Each byte takes ~2 cycles (rd_en + latch), so
        // 8 bytes * 2 cycles * 10 ns/cycle = 160 ns, plus reset + margin.
        // 300 ns gives plenty of headroom.
        #300;

        // 3. Report results
        $display("--------------------------------------------------");
        $display("Simulation complete.");
        $display("  Bytes received : %0d  (expected 8)", pixel_count);
        $display("  Value errors   : %0d", errors);

        // 4. PASS / FAIL
        if (pixel_count == 8 && all_ok) begin
            $display("  CHECK count==8 : PASS");
            $display("  CHECK values   : PASS");
            $display("OVERALL: PASS");
        end else begin
            if (pixel_count != 8)
                $display("  CHECK count==8 : FAIL  (got %0d)", pixel_count);
            else
                $display("  CHECK count==8 : PASS");
            if (!all_ok)
                $display("  CHECK values   : FAIL  (%0d mismatch(es))", errors);
            else
                $display("  CHECK values   : PASS");
            $display("OVERALL: FAIL");
        end
        $display("--------------------------------------------------");

        $finish;
    end

endmodule

sim/fifo_reader.vcd
$date
	Tue Jun 02 14:19:15 2026
$end
$version
	Icarus Verilog
$end
$timescale
	1ps
$end
$scope module fifo_reader_tb $end
$var wire 8 ! fifo_data_wire [7:0] $end
$var wire 1 " pixel_valid $end
$var wire 8 # pixel_out [7:0] $end
$var wire 1 $ fifo_rd_en $end
$var wire 1 % fifo_empty_wire $end
$var reg 1 & all_ok $end
$var reg 8 ' fifo_data_reg [7:0] $end
$var reg 4 ( fifo_rd_ptr [3:0] $end
$var reg 1 ) rclk $end
$var reg 1 * rst_n $end
$var integer 32 + errors [31:0] $end
$var integer 32 , fifo_count [31:0] $end
$var integer 32 - pixel_count [31:0] $end
$scope module uut $end
$var wire 8 . fifo_data [7:0] $end
$var wire 1 % fifo_empty $end
$var wire 1 ) rclk $end
$var wire 1 * rst_n $end
$var reg 1 / data_latched $end
$var reg 1 $ fifo_rd_en $end
$var reg 8 0 pixel_out [7:0] $end
$var reg 1 " pixel_valid $end
$upscope $end
$upscope $end
$enddefinitions $end
$comment Show the parameter values. $end
$dumpall
$end
#0
$dumpvars
b0 0
0/
bx .
b0 -
b1000 ,
b0 +
0*
0)
b0 (
bx '
1&
0%
0$
b0 #
0"
bx !
$end
#5000
1)
#10000
0)
#15000
1)
#20000
0)
1*
#25000
1$
1)
#30000
0)
#35000
1/
b111 ,
b1 (
b11000000 !
b11000000 .
b11000000 '
1)
#40000
0)
#45000
1"
b11000000 #
b11000000 0
b110 ,
b10 (
b11000001 !
b11000001 .
b11000001 '
1)
#50000
0)
#55000
b11000001 #
b11000001 0
b101 ,
b11 (
b11000010 !
b11000010 .
b11000010 '
b1 -
1)
#60000
0)
#65000
b11000010 #
b11000010 0
b100 ,
b100 (
b11000011 !
b11000011 .
b11000011 '
b10 -
1)
#70000
0)
#75000
b11000011 #
b11000011 0
b11 ,
b101 (
b11010000 !
b11010000 .
b11010000 '
b11 -
1)
#80000
0)
#85000
b11010000 #
b11010000 0
b10 ,
b110 (
b11010001 !
b11010001 .
b11010001 '
b100 -
1)
#90000
0)
#95000
b11010001 #
b11010001 0
b1 ,
b111 (
b11010010 !
b11010010 .
b11010010 '
b101 -
1)
#100000
0)
#105000
b11010010 #
b11010010 0
1%
b0 ,
b1000 (
b11010011 !
b11010011 .
b11010011 '
b110 -
1)
#110000
0)
#115000
b11010011 #
b11010011 0
0/
0$
b111 -
1)
#120000
0)
#125000
0"
b1000 -
1)
