rtl/image_generator.v
module image_generator (

    input  wire        clk,
    input  wire        rst_n,

    input  wire [9:0]  x,
    input  wire [9:0]  y,

    output reg [7:0]   pixel_out

);

always @(posedge clk or negedge rst_n) begin

    if (!rst_n) begin
        pixel_out <= 0;
    end

    else begin

        // Simple checkerboard pattern

        if ((x[5] ^ y[5]) == 1'b1)
            pixel_out <= 8'hFF;

        else
            pixel_out <= 8'h00;

    end

end

endmodule

tb/image_generator_tb.v
`timescale 1ns / 1ps

module image_generator_tb;

    reg clk;
    reg rst_n;

    reg [9:0] x;
    reg [9:0] y;

    wire [7:0] pixel_out;

    image_generator uut (
        .clk(clk),
        .rst_n(rst_n),
        .x(x),
        .y(y),
        .pixel_out(pixel_out)
    );

    always #5 clk = ~clk;

    initial begin
        $dumpfile("sim/image_generator.vcd");
        $dumpvars(0, image_generator_tb);
        
        clk = 0;
        rst_n = 0;
        x = 0;
        y = 0;

        #20;
        rst_n = 1;

        #10; x = 0;  y = 0;
        #10; x = 32; y = 0;
        #10; x = 0;  y = 32;
        #10; x = 32; y = 32;
        #10; x = 64; y = 32;

        #50;

        $finish;
    end

endmodule

sim/image_generator.vcd
$date
	Sun May 31 14:16:58 2026
$end
$version
	Icarus Verilog
$end
$timescale
	1ps
$end
$scope module image_generator_tb $end
$var wire 8 ! pixel_out [7:0] $end
$var reg 1 " clk $end
$var reg 1 # rst_n $end
$var reg 10 $ x [9:0] $end
$var reg 10 % y [9:0] $end
$scope module uut $end
$var wire 1 " clk $end
$var wire 1 # rst_n $end
$var wire 10 & x [9:0] $end
$var wire 10 ' y [9:0] $end
$var reg 8 ( pixel_out [7:0] $end
$upscope $end
$upscope $end
$enddefinitions $end
$comment Show the parameter values. $end
$dumpall
$end
#0
$dumpvars
b0 (
b0 '
b0 &
b0 %
b0 $
0#
0"
b0 !
$end
#5000
1"
#10000
0"
#15000
1"
#20000
0"
1#
#25000
1"
#30000
0"
#35000
1"
#40000
0"
b100000 $
b100000 &
#45000
b11111111 !
b11111111 (
1"
#50000
0"
b100000 %
b100000 '
b0 $
b0 &
#55000
1"
#60000
0"
b100000 $
b100000 &
#65000
b0 !
b0 (
1"
#70000
0"
b1000000 $
b1000000 &
#75000
b11111111 !
b11111111 (
1"
