rtl/bayer_to_rgb.v
module bayer_to_rgb (
    input  wire        clk,
    input  wire        rst_n,
    input  wire [7:0]  pixel_in,
    input  wire [9:0]  x,
    input  wire [9:0]  y,

    output reg [7:0]   r,
    output reg [7:0]   g,
    output reg [7:0]   b
);

always @(posedge clk or negedge rst_n) begin

    if (!rst_n) begin
        r <= 0;
        g <= 0;
        b <= 0;
    end

    else begin

        r <= 0;
        g <= 0;
        b <= 0;

        // RGGB Bayer pattern

        if ((y % 2 == 0) && (x % 2 == 0)) begin
            // Red pixel
            r <= pixel_in;
        end

        else if ((y % 2 == 0) && (x % 2 == 1)) begin
            // Green pixel
            g <= pixel_in;
        end

        else if ((y % 2 == 1) && (x % 2 == 0)) begin
            // Green pixel
            g <= pixel_in;
        end

        else begin
            // Blue pixel
            b <= pixel_in;
        end

    end

end

endmodule

rtl/image_generator.v
module image_generator (

    input  wire        clk,
    input  wire        rst_n,

    input  wire [9:0]  x,
    input  wire [9:0]  y,

    output reg [7:0]   pixel_out

);

always @(posedge clk or negedge rst_n) begin

    if (!rst_n) begin
        pixel_out <= 0;
    end

    else begin

        // Simple checkerboard pattern

        if ((x[5] ^ y[5]) == 1'b1)
            pixel_out <= 8'hFF;

        else
            pixel_out <= 8'h00;

    end

end

endmodule

rtl/vga_controller.v
module vga_controller (
    input  wire       clk,
    input  wire       rst_n,

    output reg [9:0]  x,
    output reg [9:0]  y,
    output reg        hsync,
    output reg        vsync,
    output reg        active_video
);

    // 640x480 @ 60Hz VGA timing
    localparam H_ACTIVE = 640;
    localparam H_FRONT  = 16;
    localparam H_SYNC   = 96;
    localparam H_BACK   = 48;
    localparam H_TOTAL  = 800;

    localparam V_ACTIVE = 480;
    localparam V_FRONT  = 10;
    localparam V_SYNC   = 2;
    localparam V_BACK   = 33;
    localparam V_TOTAL  = 525;

    reg [9:0] h_count;
    reg [9:0] v_count;

    always @(posedge clk or negedge rst_n) begin
        if (!rst_n) begin
            h_count <= 0;
            v_count <= 0;
        end else begin
            if (h_count == H_TOTAL - 1) begin
                h_count <= 0;

                if (v_count == V_TOTAL - 1)
                    v_count <= 0;
                else
                    v_count <= v_count + 1;
            end else begin
                h_count <= h_count + 1;
            end
        end
    end

    always @(*) begin
        active_video = (h_count < H_ACTIVE) && (v_count < V_ACTIVE);

        x = active_video ? h_count : 10'd0;
        y = active_video ? v_count : 10'd0;

        hsync = ~((h_count >= H_ACTIVE + H_FRONT) &&
                  (h_count <  H_ACTIVE + H_FRONT + H_SYNC));

        vsync = ~((v_count >= V_ACTIVE + V_FRONT) &&
                  (v_count <  V_ACTIVE + V_FRONT + V_SYNC));
    end

endmodule

rtl/isp_test_top.v
module isp_test_top (
    input  wire       clk,
    input  wire       rst_n,

    output wire       hsync,
    output wire       vsync,
    output wire       active_video,

    output wire [7:0] r,
    output wire [7:0] g,
    output wire [7:0] b
);

    wire [9:0] x;
    wire [9:0] y;
    wire [7:0] raw_pixel;

    vga_controller vga_inst (
        .clk(clk),
        .rst_n(rst_n),
        .x(x),
        .y(y),
        .hsync(hsync),
        .vsync(vsync),
        .active_video(active_video)
    );

    image_generator img_gen_inst (
        .clk(clk),
        .rst_n(rst_n),
        .x(x),
        .y(y),
        .pixel_out(raw_pixel)
    );

    bayer_to_rgb isp_inst (
        .clk(clk),
        .rst_n(rst_n),
        .pixel_in(raw_pixel),
        .x(x),
        .y(y),
        .r(r),
        .g(g),
        .b(b)
    );

endmodule

tb/isp_test_top_tb.v
`timescale 1ns / 1ps

module isp_test_top_tb;

    reg clk;
    reg rst_n;

    wire hsync;
    wire vsync;
    wire active_video;

    wire [7:0] r;
    wire [7:0] g;
    wire [7:0] b;

    isp_test_top uut (
        .clk(clk),
        .rst_n(rst_n),
        .hsync(hsync),
        .vsync(vsync),
        .active_video(active_video),
        .r(r),
        .g(g),
        .b(b)
    );

    always #20 clk = ~clk;

    initial begin
        $dumpfile("sim/isp_test_top.vcd");
        $dumpvars(0, isp_test_top_tb);

        clk = 0;
        rst_n = 0;

        #100;
        rst_n = 1;

        #100000;

        $finish;
    end

endmodule

sim/isp_test_top.vcd
$date
	Sun May 31 15:43:13 2026
$end
$version
	Icarus Verilog
$end
$timescale
	1ps
$end
$scope module isp_test_top_tb $end
$var wire 1 ! vsync $end
$var wire 8 " r [7:0] $end
$var wire 1 # hsync $end
$var wire 8 $ g [7:0] $end
$var wire 8 % b [7:0] $end
$var wire 1 & active_video $end
$var reg 1 ' clk $end
$var reg 1 ( rst_n $end
$scope module uut $end
$var wire 1 ' clk $end
$var wire 1 ( rst_n $end
$var wire 10 ) y [9:0] $end
$var wire 10 * x [9:0] $end
$var wire 1 ! vsync $end
$var wire 8 + raw_pixel [7:0] $end
$var wire 8 , r [7:0] $end
$var wire 1 # hsync $end
$var wire 8 - g [7:0] $end
$var wire 8 . b [7:0] $end
$var wire 1 & active_video $end
$scope module img_gen_inst $end
$var wire 1 ' clk $end
$var wire 1 ( rst_n $end
$var wire 10 / y [9:0] $end
$var wire 10 0 x [9:0] $end
$var reg 8 1 pixel_out [7:0] $end
$upscope $end
$scope module isp_inst $end
$var wire 1 ' clk $end
$var wire 8 2 pixel_in [7:0] $end
$var wire 1 ( rst_n $end
$var wire 10 3 y [9:0] $end
$var wire 10 4 x [9:0] $end
$var reg 8 5 b [7:0] $end
$var reg 8 6 g [7:0] $end
$var reg 8 7 r [7:0] $end
$upscope $end
$scope module vga_inst $end
$var wire 1 ' clk $end
$var wire 1 ( rst_n $end
$var parameter 32 8 H_ACTIVE $end
$var parameter 32 9 H_BACK $end
$var parameter 32 : H_FRONT $end
$var parameter 32 ; H_SYNC $end
$var parameter 32 < H_TOTAL $end
$var parameter 32 = V_ACTIVE $end
$var parameter 32 > V_BACK $end
$var parameter 32 ? V_FRONT $end
$var parameter 32 @ V_SYNC $end
$var parameter 32 A V_TOTAL $end
$var reg 1 & active_video $end
$var reg 10 B h_count [9:0] $end
$var reg 1 # hsync $end
$var reg 10 C v_count [9:0] $end
$var reg 1 ! vsync $end
$var reg 10 D x [9:0] $end
$var reg 10 E y [9:0] $end
$upscope $end
$upscope $end
$upscope $end
$enddefinitions $end
$comment Show the parameter values. $end
$dumpall
b1000001101 A
b10 @
b1010 ?
b100001 >
b111100000 =
b1100100000 <
b1100000 ;
b10000 :
b110000 9
b1010000000 8
$end
#0
$dumpvars
b0 E
b0 D
b0 C
b0 B
b0 7
b0 6
b0 5
b0 4
b0 3
b0 2
b0 1
b0 0
b0 /
b0 .
b0 -
b0 ,
b0 +
b0 *
b0 )
0(
0'
1&
b0 %
b0 $
1#
b0 "
1!
$end
#20000
1'
#40000
0'
#60000
1'
#80000
0'
#100000
b1 *
b1 0
b1 4
b1 D
b1 B
1'
1(
#120000
0'
#140000
b10 *
b10 0
b10 4
b10 D
b10 B
1'
#160000
0'
#180000
b11 *
b11 0
b11 4
b11 D
b11 B
1'
#200000
0'
#220000
b100 *
b100 0
b100 4
b100 D
b100 B
1'
#240000
0'
#260000
b101 *
b101 0
b101 4
b101 D
b101 B
1'
#280000
0'
#300000
b110 *
b110 0
b110 4
b110 D
b110 B
1'
#320000
0'
#340000
b111 *
b111 0
b111 4
b111 D
b111 B
1'
#360000
0'
#380000
b1000 *
b1000 0
b1000 4
b1000 D
b1000 B
1'
#400000
0'
#420000
b1001 *
b1001 0
b1001 4
b1001 D
b1001 B
1'
#440000
0'
#460000
b1010 *
b1010 0
b1010 4
b1010 D
b1010 B
1'
#480000
0'
#500000
b1011 *
b1011 0
b1011 4
b1011 D
b1011 B
1'
#520000
0'
#540000
b1100 *
b1100 0
b1100 4
b1100 D
b1100 B
1'
#560000
0'
#580000
b1101 *
b1101 0
b1101 4
b1101 D
b1101 B
1'
#600000
0'
#620000
b1110 *
b1110 0
b1110 4
b1110 D
b1110 B
1'
#640000
0'
#660000
b1111 *
b1111 0
b1111 4
b1111 D
b1111 B
1'
#680000
0'
#700000
b10000 *
b10000 0
b10000 4
b10000 D
b10000 B
1'
#720000
0'
#740000
b10001 *
b10001 0
b10001 4
b10001 D
b10001 B
1'
#760000
0'
#780000
b10010 *
b10010 0
b10010 4
b10010 D
b10010 B
1'
#800000
0'
#820000
b10011 *
b10011 0
b10011 4
b10011 D
b10011 B
1'
#840000
0'
#860000
b10100 *
b10100 0
b10100 4
b10100 D
b10100 B
1'
#880000
0'
#900000
b10101 *
b10101 0
b10101 4
b10101 D
b10101 B
1'
#920000
0'
#940000
b10110 *
b10110 0
b10110 4
b10110 D
b10110 B
1'
#960000
0'
#980000
b10111 *
b10111 0
b10111 4
b10111 D
b10111 B
1'
#1000000
0'
#1020000
b11000 *
b11000 0
b11000 4
b11000 D
b11000 B
1'
#1040000
0'
#1060000
b11001 *
b11001 0
b11001 4
b11001 D
b11001 B
1'
#1080000
0'
#1100000
b11010 *
b11010 0
b11010 4
b11010 D
b11010 B
1'
#1120000
0'
#1140000
b11011 *
b11011 0
b11011 4
b11011 D
b11011 B
1'
#1160000
0'
#1180000
b11100 *
b11100 0
b11100 4
b11100 D
b11100 B
1'
#1200000
0'
#1220000
b11101 *
b11101 0
b11101 4
b11101 D
b11101 B
1'
#1240000
0'
#1260000
b11110 *
b11110 0
b11110 4
b11110 D
b11110 B
1'
#1280000
0'
#1300000
b11111 *
b11111 0
b11111 4
b11111 D
b11111 B
1'
#1320000
0'
#1340000
b100000 *
b100000 0
b100000 4
b100000 D
b100000 B
1'
#1360000
0'
#1380000
b100001 *
b100001 0
b100001 4
b100001 D
b11111111 +
b11111111 1
b11111111 2
b100001 B
1'
#1400000
0'
#1420000
b100010 *
b100010 0
b100010 4
b100010 D
b100010 B
b11111111 $
b11111111 -
b11111111 6
1'
#1440000
0'
#1460000
b100011 *
b100011 0
b100011 4
b100011 D
b11111111 "
b11111111 ,
b11111111 7
b0 $
b0 -
b0 6
b100011 B
1'
#1480000
0'
#1500000
b100100 *
b100100 0
b100100 4
b100100 D
b100100 B
b11111111 $
b11111111 -
b11111111 6
b0 "
b0 ,
b0 7
1'
#1520000
0'
#1540000
b100101 *
b100101 0
b100101 4
b100101 D
b11111111 "
b11111111 ,
b11111111 7
b0 $
b0 -
b0 6
b100101 B
1'
#1560000
0'
#1580000
b100110 *
b100110 0
b100110 4
b100110 D
b100110 B
b11111111 $
b11111111 -
b11111111 6
b0 "
b0 ,
b0 7
1'
#1600000
0'
#1620000
b100111 *
b100111 0
b100111 4
b100111 D
b11111111 "
b11111111 ,
b11111111 7
b0 $
b0 -
b0 6
b100111 B
1'
#1640000
0'
#1660000
b101000 *
b101000 0
b101000 4
b101000 D
b101000 B
b11111111 $
b11111111 -
b11111111 6
b0 "
b0 ,
b0 7
1'
#1680000
0'
#1700000
b101001 *
b101001 0
b101001 4
b101001 D
b11111111 "
b11111111 ,
b11111111 7
b0 $
b0 -
b0 6
b101001 B
1'
#1720000
0'
#1740000
b101010 *
b101010 0
b101010 4
b101010 D
b101010 B
b11111111 $
b11111111 -
b11111111 6
b0 "
b0 ,
b0 7
1'
#1760000
0'
#1780000
b101011 *
b101011 0
b101011 4
b101011 D
b11111111 "
b11111111 ,
b11111111 7
b0 $
b0 -
b0 6
b101011 B
1'
#1800000
0'
#1820000
b101100 *
b101100 0
b101100 4
b101100 D
b101100 B
b11111111 $
b11111111 -
b11111111 6
b0 "
b0 ,
b0 7
1'
#1840000
0'
#1860000
b101101 *
b101101 0
b101101 4
b101101 D
b11111111 "
b11111111 ,
b11111111 7
b0 $
b0 -
b0 6
b101101 B
1'
#1880000
0'
#1900000
b101110 *
b101110 0
b101110 4
b101110 D
b101110 B
b11111111 $
b11111111 -
b11111111 6
b0 "
b0 ,
b0 7
1'
#1920000
0'
#1940000
b101111 *
b101111 0
b101111 4
b101111 D
b11111111 "
b11111111 ,
b11111111 7
b0 $
b0 -
b0 6
b101111 B
1'
#1960000
0'
#1980000
b110000 *
b110000 0
b110000 4
b110000 D
b110000 B
b11111111 $
b11111111 -
b11111111 6
b0 "
b0 ,
b0 7
1'
#2000000
0'
#2020000
b110001 *
b110001 0
b110001 4
b110001 D
b11111111 "
b11111111 ,
b11111111 7
b0 $
b0 -
b0 6
b110001 B
1'
#2040000
0'
#2060000
b110010 *
b110010 0
b110010 4
b110010 D
b110010 B
b11111111 $
b11111111 -
b11111111 6
b0 "
b0 ,
b0 7
1'
#2080000
0'
#2100000
b110011 *
b110011 0
b110011 4
b110011 D
b11111111 "
b11111111 ,
b11111111 7
b0 $
b0 -
b0 6
b110011 B
1'
#2120000
0'
#2140000
b110100 *
b110100 0
b110100 4
b110100 D
b110100 B
b11111111 $
b11111111 -
b11111111 6
b0 "
b0 ,
b0 7
1'
#2160000
0'
#2180000
b110101 *
b110101 0
b110101 4
b110101 D
b11111111 "
b11111111 ,
b11111111 7
b0 $
b0 -
b0 6
b110101 B
1'
#2200000
0'
#2220000
b110110 *
b110110 0
b110110 4
b110110 D
b110110 B
b11111111 $
b11111111 -
b11111111 6
b0 "
b0 ,
b0 7
1'
#2240000
0'
#2260000
b110111 *
b110111 0
b110111 4
b110111 D
b11111111 "
b11111111 ,
b11111111 7
b0 $
b0 -
b0 6
b110111 B
1'
#2280000
0'
#2300000
b111000 *
b111000 0
b111000 4
b111000 D
b111000 B
b11111111 $
b11111111 -
b11111111 6
b0 "
b0 ,
b0 7
1'
#2320000
0'
#2340000
b111001 *
b111001 0
b111001 4
b111001 D
b11111111 "
b11111111 ,
b11111111 7
b0 $
b0 -
b0 6
b111001 B
1'
#2360000
0'
#2380000
b111010 *
b111010 0
b111010 4
b111010 D
b111010 B
b11111111 $
b11111111 -
b11111111 6
b0 "
b0 ,
b0 7
1'
#2400000
0'
#2420000
b111011 *
b111011 0
b111011 4
b111011 D
b11111111 "
b11111111 ,
b11111111 7
b0 $
b0 -
b0 6
b111011 B
1'
#2440000
0'
#2460000
b111100 *
b111100 0
b111100 4
b111100 D
b111100 B
b11111111 $
b11111111 -
b11111111 6
b0 "
b0 ,
b0 7
1'
#2480000
0'
#2500000
b111101 *
b111101 0
b111101 4
b111101 D
b11111111 "
b11111111 ,
b11111111 7
b0 $
b0 -
b0 6
b111101 B
1'
#2520000
0'
#2540000
b111110 *
b111110 0
b111110 4
b111110 D
b111110 B
b11111111 $
b11111111 -
b11111111 6
b0 "
b0 ,
b0 7
1'
#2560000
0'
#2580000
b111111 *
b111111 0
b111111 4
b111111 D
b11111111 "
b11111111 ,
b11111111 7
b0 $
b0 -
b0 6
b111111 B
1'
#2600000
0'
#2620000
b1000000 *
b1000000 0
b1000000 4
b1000000 D
b1000000 B
b11111111 $
b11111111 -
b11111111 6
b0 "
b0 ,
b0 7
1'
#2640000
0'
#2660000
b1000001 *
b1000001 0
b1000001 4
b1000001 D
b11111111 "
b11111111 ,
b11111111 7
b0 $
b0 -
b0 6
b0 +
b0 1
b0 2
b1000001 B
1'
#2680000
0'
#2700000
b1000010 *
b1000010 0
b1000010 4
b1000010 D
b1000010 B
b0 "
b0 ,
b0 7
1'
#2720000
0'
#2740000
b1000011 *
b1000011 0
b1000011 4
b1000011 D
b1000011 B
1'
#2760000
0'
#2780000
b1000100 *
b1000100 0
b1000100 4
b1000100 D
b1000100 B
1'
#2800000
0'
#2820000
b1000101 *
b1000101 0
b1000101 4
b1000101 D
b1000101 B
1'
#2840000
0'
#2860000
b1000110 *
b1000110 0
b1000110 4
b1000110 D
b1000110 B
1'
#2880000
0'
#2900000
b1000111 *
b1000111 0
b1000111 4
b1000111 D
b1000111 B
1'
#2920000
0'
#2940000
b1001000 *
b1001000 0
b1001000 4
b1001000 D
b1001000 B
1'
#2960000
0'
#2980000
b1001001 *
b1001001 0
b1001001 4
b1001001 D
b1001001 B
1'
#3000000
0'
#3020000
b1001010 *
b1001010 0
b1001010 4
b1001010 D
b1001010 B
1'
#3040000
0'
#3060000
b1001011 *
b1001011 0
b1001011 4
b1001011 D
b1001011 B
1'
#3080000
0'
#3100000
b1001100 *
b1001100 0
b1001100 4
b1001100 D
b1001100 B
1'
#3120000
0'
#3140000
b1001101 *
b1001101 0
b1001101 4
b1001101 D
b1001101 B
1'
#3160000
0'
#3180000
b1001110 *
b1001110 0
b1001110 4
b1001110 D
b1001110 B
1'
#3200000
0'
#3220000
b1001111 *
b1001111 0
b1001111 4
b1001111 D
b1001111 B
1'
#3240000
0'
#3260000
b1010000 *
b1010000 0
b1010000 4
b1010000 D
b1010000 B
1'
#3280000
0'
#3300000
b1010001 *
b1010001 0
b1010001 4
b1010001 D
b1010001 B
1'
#3320000
0'
#3340000
b1010010 *
b1010010 0
b1010010 4
b1010010 D
b1010010 B
1'
#3360000
0'
#3380000
b1010011 *
b1010011 0
b1010011 4
b1010011 D
b1010011 B
1'
#3400000
0'
#3420000
b1010100 *
b1010100 0
b1010100 4
b1010100 D
b1010100 B
1'
#3440000
0'
#3460000
b1010101 *
b1010101 0
b1010101 4
b1010101 D
b1010101 B
1'
#3480000
0'
#3500000
b1010110 *
b1010110 0
b1010110 4
b1010110 D
b1010110 B
1'
#3520000
0'
#3540000
b1010111 *
b1010111 0
b1010111 4
b1010111 D
b1010111 B
1'
#3560000
0'
#3580000
b1011000 *
b1011000 0
b1011000 4
b1011000 D
b1011000 B
1'
#3600000
0'
#3620000
b1011001 *
b1011001 0
b1011001 4
b1011001 D
b1011001 B
1'
#3640000
0'
#3660000
b1011010 *
b1011010 0
b1011010 4
b1011010 D
b1011010 B
1'
#3680000
0'
#3700000
b1011011 *
b1011011 0
b1011011 4
b1011011 D
b1011011 B
1'
#3720000
0'
#3740000
b1011100 *
b1011100 0
b1011100 4
b1011100 D
b1011100 B
1'
#3760000
0'
#3780000
b1011101 *
b1011101 0
b1011101 4
b1011101 D
b1011101 B
1'
#3800000
0'
#3820000
b1011110 *
b1011110 0
b1011110 4
b1011110 D
b1011110 B
1'
#3840000
0'
#3860000
b1011111 *
b1011111 0
b1011111 4
b1011111 D
b1011111 B
1'
#3880000
0'
#3900000
b1100000 *
b1100000 0
b1100000 4
b1100000 D
b1100000 B
1'
#3920000
0'
#3940000
b1100001 *
b1100001 0
b1100001 4
b1100001 D
b11111111 +
b11111111 1
b11111111 2
b1100001 B
1'
#3960000
0'
#3980000
b1100010 *
b1100010 0
b1100010 4
b1100010 D
b1100010 B
b11111111 $
b11111111 -
b11111111 6
1'
#4000000
0'
#4020000
b1100011 *
b1100011 0
b1100011 4
b1100011 D
b11111111 "
b11111111 ,
b11111111 7
b0 $
b0 -
b0 6
b1100011 B
1'
#4040000
0'
#4060000
b1100100 *
b1100100 0
b1100100 4
b1100100 D
b1100100 B
b11111111 $
b11111111 -
b11111111 6
b0 "
b0 ,
b0 7
1'
#4080000
0'
#4100000
b1100101 *
b1100101 0
b1100101 4
b1100101 D
b11111111 "
b11111111 ,
b11111111 7
b0 $
b0 -
b0 6
b1100101 B
1'
#4120000
0'
#4140000
b1100110 *
b1100110 0
b1100110 4
b1100110 D
b1100110 B
b11111111 $
b11111111 -
b11111111 6
b0 "
b0 ,
b0 7
1'
#4160000
0'
#4180000
b1100111 *
b1100111 0
b1100111 4
b1100111 D
b11111111 "
b11111111 ,
b11111111 7
b0 $
b0 -
b0 6
b1100111 B
1'
#4200000
0'
#4220000
b1101000 *
b1101000 0
b1101000 4
b1101000 D
b1101000 B
b11111111 $
b11111111 -
b11111111 6
b0 "
b0 ,
b0 7
1'
#4240000
0'
#4260000
b1101001 *
b1101001 0
b1101001 4
b1101001 D
b11111111 "
b11111111 ,
b11111111 7
b0 $
b0 -
b0 6
b1101001 B
1'
#4280000
0'
#4300000
b1101010 *
b1101010 0
b1101010 4
b1101010 D
b1101010 B
b11111111 $
b11111111 -
b11111111 6
b0 "
b0 ,
b0 7
1'
#4320000
0'
#4340000
b1101011 *
b1101011 0
b1101011 4
b1101011 D
b11111111 "
b11111111 ,
b11111111 7
b0 $
b0 -
b0 6
b1101011 B
1'
#4360000
0'
#4380000
b1101100 *
b1101100 0
b1101100 4
b1101100 D
b1101100 B
b11111111 $
b11111111 -
b11111111 6
b0 "
b0 ,
b0 7
1'
#4400000
0'
#4420000
b1101101 *
b1101101 0
b1101101 4
b1101101 D
b11111111 "
b11111111 ,
b11111111 7
b0 $
b0 -
b0 6
b1101101 B
1'
#4440000
0'
#4460000
b1101110 *
b1101110 0
b1101110 4
b1101110 D
b1101110 B
b11111111 $
b11111111 -
b11111111 6
b0 "
b0 ,
b0 7
1'
#4480000
0'
#4500000
b1101111 *
b1101111 0
b1101111 4
b1101111 D
b11111111 "
b11111111 ,
b11111111 7
b0 $
b0 -
b0 6
b1101111 B
1'
#4520000
0'
#4540000
b1110000 *
b1110000 0
b1110000 4
b1110000 D
b1110000 B
b11111111 $
b11111111 -
b11111111 6
b0 "
b0 ,
b0 7
1'
#4560000
0'
#4580000
b1110001 *
b1110001 0
b1110001 4
b1110001 D
b11111111 "
b11111111 ,
b11111111 7
b0 $
b0 -
b0 6
b1110001 B
1'
#4600000
0'
#4620000
b1110010 *
b1110010 0
b1110010 4
b1110010 D
b1110010 B
b11111111 $
b11111111 -
b11111111 6
b0 "
b0 ,
b0 7
1'
#4640000
0'
#4660000
b1110011 *
b1110011 0
b1110011 4
b1110011 D
b11111111 "
b11111111 ,
b11111111 7
b0 $
b0 -
b0 6
b1110011 B
1'
#4680000
0'
#4700000
b1110100 *
b1110100 0
b1110100 4
b1110100 D
b1110100 B
b11111111 $
b11111111 -
b11111111 6
b0 "
b0 ,
b0 7
1'
#4720000
0'
#4740000
b1110101 *
b1110101 0
b1110101 4
b1110101 D
b11111111 "
b11111111 ,
b11111111 7
b0 $
b0 -
b0 6
b1110101 B
1'
#4760000
0'
#4780000
b1110110 *
b1110110 0
b1110110 4
b1110110 D
b1110110 B
b11111111 $
b11111111 -
b11111111 6
b0 "
b0 ,
b0 7
1'
#4800000
0'
#4820000
b1110111 *
b1110111 0
b1110111 4
b1110111 D
b11111111 "
b11111111 ,
b11111111 7
b0 $
b0 -
b0 6
b1110111 B
1'
#4840000
0'
#4860000
b1111000 *
b1111000 0
b1111000 4
b1111000 D
b1111000 B
b11111111 $
b11111111 -
b11111111 6
b0 "
b0 ,
b0 7
1'
#4880000
0'
#4900000
b1111001 *
b1111001 0
b1111001 4
b1111001 D
b11111111 "
b11111111 ,
b11111111 7
b0 $
b0 -
b0 6
b1111001 B
1'
#4920000
0'
#4940000
b1111010 *
b1111010 0
b1111010 4
b1111010 D
b1111010 B
b11111111 $
b11111111 -
b11111111 6
b0 "
b0 ,
b0 7
1'
#4960000
0'
#4980000
b1111011 *
b1111011 0
b1111011 4
b1111011 D
b11111111 "
b11111111 ,
b11111111 7
b0 $
b0 -
b0 6
b1111011 B
1'
#5000000
0'
#5020000
b1111100 *
b1111100 0
b1111100 4
b1111100 D
b1111100 B
b11111111 $
b11111111 -
b11111111 6
b0 "
b0 ,
b0 7
1'
#5040000
0'
#5060000
b1111101 *
b1111101 0
b1111101 4
b1111101 D
b11111111 "
b11111111 ,
b11111111 7
b0 $
b0 -
b0 6
b1111101 B
1'
#5080000
0'
#5100000
b1111110 *
b1111110 0
b1111110 4
b1111110 D
b1111110 B
b11111111 $
b11111111 -
b11111111 6
b0 "
b0 ,
b0 7
1'
#5120000
0'
#5140000
b1111111 *
b1111111 0
b1111111 4
b1111111 D
b11111111 "
b11111111 ,
b11111111 7
b0 $
b0 -
b0 6
b1111111 B
1'
#5160000
0'
#5180000
b10000000 *
b10000000 0
b10000000 4
b10000000 D
b10000000 B
b11111111 $
b11111111 -
b11111111 6
b0 "
b0 ,
b0 7
1'
#5200000
0'
#5220000
b10000001 *
b10000001 0
b10000001 4
b10000001 D
b11111111 "
b11111111 ,
b11111111 7
b0 $
b0 -
b0 6
b0 +
b0 1
b0 2
b10000001 B
1'
#5240000
0'
#5260000
b10000010 *
b10000010 0
b10000010 4
b10000010 D
b10000010 B
b0 "
b0 ,
b0 7
1'
#5280000
0'
#5300000
b10000011 *
b10000011 0
b10000011 4
b10000011 D
b10000011 B
1'
#5320000
0'
#5340000
b10000100 *
b10000100 0
b10000100 4
b10000100 D
b10000100 B
1'
#5360000
0'
#5380000
b10000101 *
b10000101 0
b10000101 4
b10000101 D
b10000101 B
1'
#5400000
0'
#5420000
b10000110 *
b10000110 0
b10000110 4
b10000110 D
b10000110 B
1'
#5440000
0'
#5460000
b10000111 *
b10000111 0
b10000111 4
b10000111 D
b10000111 B
1'
#5480000
0'
#5500000
b10001000 *
b10001000 0
b10001000 4
b10001000 D
b10001000 B
1'
#5520000
0'
#5540000
b10001001 *
b10001001 0
b10001001 4
b10001001 D
b10001001 B
1'
#5560000
0'
#5580000
b10001010 *
b10001010 0
b10001010 4
b10001010 D
b10001010 B
1'
#5600000
0'
#5620000
b10001011 *
b10001011 0
b10001011 4
b10001011 D
b10001011 B
1'
#5640000
0'
#5660000
b10001100 *
b10001100 0
b10001100 4
b10001100 D
b10001100 B
1'
#5680000
0'
#5700000
b10001101 *
b10001101 0
b10001101 4
b10001101 D
b10001101 B
1'
#5720000
0'
#5740000
b10001110 *
b10001110 0
b10001110 4
b10001110 D
b10001110 B
1'
#5760000
0'
#5780000
b10001111 *
b10001111 0
b10001111 4
b10001111 D
b10001111 B
1'
#5800000
0'
#5820000
b10010000 *
b10010000 0
b10010000 4
b10010000 D
b10010000 B
1'
#5840000
0'
#5860000
b10010001 *
b10010001 0
b10010001 4
b10010001 D
b10010001 B
1'
#5880000
0'
#5900000
b10010010 *
b10010010 0
b10010010 4
b10010010 D
b10010010 B
1'
#5920000
0'
#5940000
b10010011 *
b10010011 0
b10010011 4
b10010011 D
b10010011 B
1'
#5960000
0'
#5980000
b10010100 *
b10010100 0
b10010100 4
b10010100 D
b10010100 B
1'
#6000000
0'
#6020000
b10010101 *
b10010101 0
b10010101 4
b10010101 D
b10010101 B
1'
#6040000
0'
#6060000
b10010110 *
b10010110 0
b10010110 4
b10010110 D
b10010110 B
1'
#6080000
0'
#6100000
b10010111 *
b10010111 0
b10010111 4
b10010111 D
b10010111 B
1'
#6120000
0'
#6140000
b10011000 *
b10011000 0
b10011000 4
b10011000 D
b10011000 B
1'
#6160000
0'
#6180000
b10011001 *
b10011001 0
b10011001 4
b10011001 D
b10011001 B
1'
#6200000
0'
#6220000
b10011010 *
b10011010 0
b10011010 4
b10011010 D
b10011010 B
1'
#6240000
0'
#6260000
b10011011 *
b10011011 0
b10011011 4
b10011011 D
b10011011 B
1'
#6280000
0'
#6300000
b10011100 *
b10011100 0
b10011100 4
b10011100 D
b10011100 B
1'
#6320000
0'
#6340000
b10011101 *
b10011101 0
b10011101 4
b10011101 D
b10011101 B
1'
#6360000
0'
#6380000
b10011110 *
b10011110 0
b10011110 4
b10011110 D
b10011110 B
1'
#6400000
0'
#6420000
b10011111 *
b10011111 0
b10011111 4
b10011111 D
b10011111 B
1'
#6440000
0'
#6460000
b10100000 *
b10100000 0
b10100000 4
b10100000 D
b10100000 B
1'
#6480000
0'
#6500000
b10100001 *
b10100001 0
b10100001 4
b10100001 D
b11111111 +
b11111111 1
b11111111 2
b10100001 B
1'
#6520000
0'
#6540000
b10100010 *
b10100010 0
b10100010 4
b10100010 D
b10100010 B
b11111111 $
b11111111 -
b11111111 6
1'
#6560000
0'
#6580000
b10100011 *
b10100011 0
b10100011 4
b10100011 D
b11111111 "
b11111111 ,
b11111111 7
b0 $
b0 -
b0 6
b10100011 B
1'
#6600000
0'
#6620000
b10100100 *
b10100100 0
b10100100 4
b10100100 D
b10100100 B
b11111111 $
b11111111 -
b11111111 6
b0 "
b0 ,
b0 7
1'
#6640000
0'
#6660000
b10100101 *
b10100101 0
b10100101 4
b10100101 D
b11111111 "
b11111111 ,
b11111111 7
b0 $
b0 -
b0 6
b10100101 B
1'
#6680000
0'
#6700000
b10100110 *
b10100110 0
b10100110 4
b10100110 D
b10100110 B
b11111111 $
b11111111 -
b11111111 6
b0 "
b0 ,
b0 7
1'
#6720000
0'
#6740000
b10100111 *
b10100111 0
b10100111 4
b10100111 D
b11111111 "
b11111111 ,
b11111111 7
b0 $
b0 -
b0 6
b10100111 B
1'
#6760000
0'
#6780000
b10101000 *
b10101000 0
b10101000 4
b10101000 D
b10101000 B
b11111111 $
b11111111 -
b11111111 6
b0 "
b0 ,
b0 7
1'
#6800000
0'
#6820000
b10101001 *
b10101001 0
b10101001 4
b10101001 D
b11111111 "
b11111111 ,
b11111111 7
b0 $
b0 -
b0 6
b10101001 B
1'
#6840000
0'
#6860000
b10101010 *
b10101010 0
b10101010 4
b10101010 D
b10101010 B
b11111111 $
b11111111 -
b11111111 6
b0 "
b0 ,
b0 7
1'
#6880000
0'
#6900000
b10101011 *
b10101011 0
b10101011 4
b10101011 D
b11111111 "
b11111111 ,
b11111111 7
b0 $
b0 -
b0 6
b10101011 B
1'
#6920000
0'
#6940000
b10101100 *
b10101100 0
b10101100 4
b10101100 D
b10101100 B
b11111111 $
b11111111 -
b11111111 6
b0 "
b0 ,
b0 7
1'
#6960000
0'
#6980000
b10101101 *
b10101101 0
b10101101 4
b10101101 D
b11111111 "
b11111111 ,
b11111111 7
b0 $
b0 -
b0 6
b10101101 B
1'
#7000000
0'
#7020000
b10101110 *
b10101110 0
b10101110 4
b10101110 D
b10101110 B
b11111111 $
b11111111 -
b11111111 6
b0 "
b0 ,
b0 7
1'
#7040000
0'
#7060000
b10101111 *
b10101111 0
b10101111 4
b10101111 D
b11111111 "
b11111111 ,
b11111111 7
b0 $
b0 -
b0 6
b10101111 B
1'
#7080000
0'
#7100000
b10110000 *
b10110000 0
b10110000 4
b10110000 D
b10110000 B
b11111111 $
b11111111 -
b11111111 6
b0 "
b0 ,
b0 7
1'
#7120000
0'
