rtl/main_fsm.v
module main_fsm (
    input  wire clk,
    input  wire rst_n,

    input  wire trigger,
    input  wire capture_done,
    input  wire fifo_read_done,
    input  wire isp_done,
    input  wire display_done,
    input  wire error_flag,

    output reg  camera_enable,
    output reg  fifo_read_enable,
    output reg  isp_enable,
    output reg  display_enable
);

    localparam IDLE           = 3'd0;
    localparam WAIT_TRIGGER   = 3'd1;
    localparam CAMERA_CAPTURE = 3'd2;
    localparam READ_FIFO      = 3'd3;
    localparam ISP_PROCESS    = 3'd4;
    localparam DISPLAY        = 3'd5;
    localparam ERROR          = 3'd6;

    reg [2:0] state, next_state;

    always @(posedge clk or negedge rst_n) begin
        if (!rst_n)
            state <= IDLE;
        else
            state <= next_state;
    end

    always @(*) begin
        next_state = state;

        case (state)
            IDLE:
                next_state = WAIT_TRIGGER;

            WAIT_TRIGGER:
                if (trigger)
                    next_state = CAMERA_CAPTURE;

            CAMERA_CAPTURE:
                if (error_flag)
                    next_state = ERROR;
                else if (capture_done)
                    next_state = READ_FIFO;

            READ_FIFO:
                if (error_flag)
                    next_state = ERROR;
                else if (fifo_read_done)
                    next_state = ISP_PROCESS;

            ISP_PROCESS:
                if (error_flag)
                    next_state = ERROR;
                else if (isp_done)
                    next_state = DISPLAY;

            DISPLAY:
                if (display_done)
                    next_state = WAIT_TRIGGER;

            ERROR:
                next_state = IDLE;

            default:
                next_state = IDLE;
        endcase
    end

    always @(*) begin
        camera_enable    = 1'b0;
        fifo_read_enable = 1'b0;
        isp_enable       = 1'b0;
        display_enable   = 1'b0;

        case (state)
            CAMERA_CAPTURE:
                camera_enable = 1'b1;

            READ_FIFO:
                fifo_read_enable = 1'b1;

            ISP_PROCESS:
                isp_enable = 1'b1;

            DISPLAY:
                display_enable = 1'b1;
        endcase
    end

endmodule

tb/main_fsm_tb.v
`timescale 1ns / 1ps

module main_fsm_tb;

    reg clk;
    reg rst_n;

    reg trigger;
    reg capture_done;
    reg fifo_read_done;
    reg isp_done;
    reg display_done;
    reg error_flag;

    wire camera_enable;
    wire fifo_read_enable;
    wire isp_enable;
    wire display_enable;

    main_fsm uut (
        .clk(clk),
        .rst_n(rst_n),

        .trigger(trigger),
        .capture_done(capture_done),
        .fifo_read_done(fifo_read_done),
        .isp_done(isp_done),
        .display_done(display_done),
        .error_flag(error_flag),

        .camera_enable(camera_enable),
        .fifo_read_enable(fifo_read_enable),
        .isp_enable(isp_enable),
        .display_enable(display_enable)
    );

    always #5 clk = ~clk;

    initial begin
       $dumpfile("sim/main_fsm.vcd");
       $dumpvars(0, main_fsm_tb);
       
        clk = 0;
        rst_n = 0;

        trigger = 0;
        capture_done = 0;
        fifo_read_done = 0;
        isp_done = 0;
        display_done = 0;
        error_flag = 0;

        #20;
        rst_n = 1;

        #20;
        trigger = 1;

        #20;
        trigger = 0;

        #40;
        capture_done = 1;

        #20;
        capture_done = 0;

        #40;
        fifo_read_done = 1;

        #20;
        fifo_read_done = 0;

        #40;
        isp_done = 1;

        #20;
        isp_done = 0;

        #40;
        display_done = 1;

        #20;
        display_done = 0;

        #100;

        $finish;
    end

endmodule

sim/main_fsm.vcd
$date
	Sun May 31 14:01:30 2026
$end
$version
	Icarus Verilog
$end
$timescale
	1ps
$end
$scope module main_fsm_tb $end
$var wire 1 ! isp_enable $end
$var wire 1 " fifo_read_enable $end
$var wire 1 # display_enable $end
$var wire 1 $ camera_enable $end
$var reg 1 % capture_done $end
$var reg 1 & clk $end
$var reg 1 ' display_done $end
$var reg 1 ( error_flag $end
$var reg 1 ) fifo_read_done $end
$var reg 1 * isp_done $end
$var reg 1 + rst_n $end
$var reg 1 , trigger $end
$scope module uut $end
$var wire 1 % capture_done $end
$var wire 1 & clk $end
$var wire 1 ' display_done $end
$var wire 1 ( error_flag $end
$var wire 1 ) fifo_read_done $end
$var wire 1 * isp_done $end
$var wire 1 + rst_n $end
$var wire 1 , trigger $end
$var parameter 3 - CAMERA_CAPTURE $end
$var parameter 3 . DISPLAY $end
$var parameter 3 / ERROR $end
$var parameter 3 0 IDLE $end
$var parameter 3 1 ISP_PROCESS $end
$var parameter 3 2 READ_FIFO $end
$var parameter 3 3 WAIT_TRIGGER $end
$var reg 1 $ camera_enable $end
$var reg 1 # display_enable $end
$var reg 1 " fifo_read_enable $end
$var reg 1 ! isp_enable $end
$var reg 3 4 next_state [2:0] $end
$var reg 3 5 state [2:0] $end
$upscope $end
$upscope $end
$enddefinitions $end
$comment Show the parameter values. $end
$dumpall
b1 3
b11 2
b100 1
b0 0
b110 /
b101 .
b10 -
$end
#0
$dumpvars
b0 5
b1 4
0,
0+
0*
0)
0(
0'
0&
0%
0$
0#
0"
0!
$end
#5000
1&
#10000
0&
#15000
1&
#20000
0&
1+
#25000
b1 5
1&
#30000
0&
#35000
1&
#40000
b10 4
0&
1,
#45000
1$
b10 5
1&
#50000
0&
#55000
1&
#60000
0&
0,
#65000
1&
#70000
0&
#75000
1&
#80000
0&
#85000
1&
#90000
0&
#95000
1&
#100000
b11 4
0&
1%
#105000
1"
0$
b11 5
1&
#110000
0&
#115000
1&
#120000
0&
0%
#125000
1&
#130000
0&
#135000
1&
#140000
0&
#145000
1&
#150000
0&
#155000
1&
#160000
b100 4
0&
1)
#165000
1!
0"
b100 5
1&
#170000
0&
#175000
1&
#180000
0&
0)
#185000
1&
#190000
0&
#195000
1&
#200000
0&
#205000
1&
#210000
0&
#215000
1&
#220000
b101 4
0&
1*
#225000
1#
0!
b101 5
1&
#230000
0&
#235000
1&
#240000
0&
0*
#245000
1&
#250000
0&
#255000
1&
#260000
0&
#265000
1&
#270000
0&
#275000
1&
#280000
b1 4
0&
1'
#285000
0#
b1 5
1&
#290000
0&
#295000
1&
#300000
0&
0'
