rtl/main_fsm.v
module main_fsm #(
    parameter TIMEOUT_LIMIT = 8'd200,  // cycles before timeout fires; override in TB
    parameter MAX_RETRIES   = 2'd3     // error retries before fatal lock
) (
    input  wire clk,
    input  wire rst_n,

    input  wire trigger,
    input  wire capture_done,
    input  wire fifo_read_done,
    input  wire isp_done,
    input  wire display_done,
    input  wire error_flag,

    // Stage-ready handshake inputs
    input  wire capture_ready,
    input  wire isp_ready,
    input  wire display_ready,

    output reg        camera_enable,
    output reg        fifo_read_enable,
    output reg        isp_enable,
    output reg        display_enable,

    // Debug / status outputs
    output wire [2:0] state_out,
    output wire [2:0] error_code_out,
    output wire [1:0] retry_count_out,
    output wire       timeout_flag
);

    localparam IDLE           = 3'd0;
    localparam WAIT_TRIGGER   = 3'd1;
    localparam CAMERA_CAPTURE = 3'd2;
    localparam READ_FIFO      = 3'd3;
    localparam ISP_PROCESS    = 3'd4;
    localparam DISPLAY        = 3'd5;
    localparam ERROR          = 3'd6;

    // error_code values — record which stage failed
    localparam ERR_NONE    = 3'd0;
    localparam ERR_CAPTURE = 3'd1;
    localparam ERR_FIFO    = 3'd2;
    localparam ERR_ISP     = 3'd3;
    localparam ERR_DISPLAY = 3'd4;
    localparam ERR_TIMEOUT = 3'd5;

    reg [2:0] state, next_state;

    reg [2:0] error_code;
    reg [1:0] retry_count;

    // Timeout tracking
    reg [7:0] timeout_counter;
    wire      timeout_hit = (timeout_counter >= TIMEOUT_LIMIT);

    assign state_out       = state;
    assign error_code_out  = error_code;
    assign retry_count_out = retry_count;
    assign timeout_flag    = timeout_hit;

    always @(posedge clk or negedge rst_n) begin
        if (!rst_n) begin
            state           <= IDLE;
            error_code      <= 3'd0;
            retry_count     <= 2'd0;
            timeout_counter <= 8'd0;
        end else begin
            state <= next_state;

            // Record which state caused the ERROR transition, and whether it was a timeout
            if (next_state == ERROR && state != ERROR) begin
                if (timeout_hit) begin
                    error_code <= ERR_TIMEOUT;
                end else begin
                    case (state)
                        CAMERA_CAPTURE: error_code <= ERR_CAPTURE;
                        READ_FIFO:      error_code <= ERR_FIFO;
                        ISP_PROCESS:    error_code <= ERR_ISP;
                        DISPLAY:        error_code <= ERR_DISPLAY;
                        default:        error_code <= ERR_NONE;
                    endcase
                end
            end

            // Increment retry count on each ERROR->WAIT_TRIGGER (a retry attempt)
            // Reset it on a successful DISPLAY->WAIT_TRIGGER (pipeline completed cleanly)
            if (state == DISPLAY && next_state == WAIT_TRIGGER)
                retry_count <= 2'd0;
            else if (state == ERROR && next_state == WAIT_TRIGGER)
                retry_count <= retry_count + 2'd1;
        end
    end

    // Timeout counter — resets whenever the FSM is about to change state
    always @(posedge clk or negedge rst_n) begin
        if (!rst_n) begin
            timeout_counter <= 8'd0;
        end else begin
            if (state != next_state)
                // A transition is happening this clock cycle — reset counter for the new state
                timeout_counter <= 8'd0;
            else if (timeout_counter < TIMEOUT_LIMIT)
                timeout_counter <= timeout_counter + 8'd1;
            // If counter == TIMEOUT_LIMIT, hold — next_state logic drives ERROR
        end
    end

    always @(*) begin
        next_state = state;

        case (state)
            IDLE:
                next_state = WAIT_TRIGGER;

            WAIT_TRIGGER:
                if (trigger && capture_ready)
                    next_state = CAMERA_CAPTURE;

            CAMERA_CAPTURE:
                if (error_flag || timeout_hit)
                    next_state = ERROR;
                else if (capture_done)
                    next_state = READ_FIFO;

            READ_FIFO:
                if (error_flag || timeout_hit)
                    next_state = ERROR;
                else if (fifo_read_done)
                    next_state = ISP_PROCESS;

            ISP_PROCESS:
                if (error_flag || timeout_hit)
                    next_state = ERROR;
                else if (isp_done && display_ready)
                    next_state = DISPLAY;

            DISPLAY:
                if (timeout_hit)
                    next_state = ERROR;
                else if (display_done)
                    next_state = WAIT_TRIGGER;

            ERROR:
                // If retries are exhausted, stay in ERROR (fatal lock — only rst_n escapes)
                // Otherwise return to WAIT_TRIGGER for another attempt
                if (retry_count >= MAX_RETRIES)
                    next_state = ERROR;
                else
                    next_state = WAIT_TRIGGER;

            default:
                next_state = IDLE;
        endcase
    end

    always @(*) begin
        camera_enable    = 1'b0;
        fifo_read_enable = 1'b0;
        isp_enable       = 1'b0;
        display_enable   = 1'b0;

        case (state)
            CAMERA_CAPTURE:
                camera_enable = 1'b1;

            READ_FIFO:
                fifo_read_enable = 1'b1;

            ISP_PROCESS:
                isp_enable = isp_ready;

            DISPLAY:
                display_enable = display_ready;
        endcase
    end

endmodule

tb/main_fsm_tb.v
`timescale 1ns / 1ps

module main_fsm_tb;

    reg clk;
    reg rst_n;

    reg trigger;
    reg capture_done;
    reg fifo_read_done;
    reg isp_done;
    reg display_done;
    reg error_flag;

    // Stage-ready handshake inputs
    reg capture_ready;
    reg isp_ready;
    reg display_ready;

    wire camera_enable;
    wire fifo_read_enable;
    wire isp_enable;
    wire display_enable;

    // Debug / status outputs
    wire [2:0] state_out;
    wire [2:0] error_code_out;
    wire [1:0] retry_count_out;
    wire       timeout_flag;

    // Latch registers — capture transient events so checks work after the fact
    reg error_seen;      // set the moment state_out becomes ERROR
    reg timeout_seen;    // set the moment timeout_flag goes high

    initial begin error_seen = 0; timeout_seen = 0; end

    always @(posedge clk) begin
        if (state_out == 3'd6) error_seen   <= 1'b1;
        if (timeout_flag)      timeout_seen <= 1'b1;
    end

    // Short TIMEOUT_LIMIT for fast simulation; MAX_RETRIES=2 to test exhaustion quickly
    main_fsm #(.TIMEOUT_LIMIT(8'd10), .MAX_RETRIES(2'd2)) uut (
        .clk(clk),
        .rst_n(rst_n),

        .trigger(trigger),
        .capture_done(capture_done),
        .fifo_read_done(fifo_read_done),
        .isp_done(isp_done),
        .display_done(display_done),
        .error_flag(error_flag),

        .capture_ready(capture_ready),
        .isp_ready(isp_ready),
        .display_ready(display_ready),

        .camera_enable(camera_enable),
        .fifo_read_enable(fifo_read_enable),
        .isp_enable(isp_enable),
        .display_enable(display_enable),

        .state_out(state_out),
        .error_code_out(error_code_out),
        .retry_count_out(retry_count_out),
        .timeout_flag(timeout_flag)
    );

    always #5 clk = ~clk;

    initial begin
       $dumpfile("sim/main_fsm.vcd");
       $dumpvars(0, main_fsm_tb);
       
        clk = 0;
        rst_n = 0;

        trigger = 0;
        capture_done = 0;
        fifo_read_done = 0;
        isp_done = 0;
        display_done = 0;
        error_flag = 0;

        // All stages ready by default for happy-path test
        capture_ready = 1;
        isp_ready     = 1;
        display_ready = 1;

        #20;
        rst_n = 1;
        $display("[%0t] Reset released. state=%0d error_code=%0d retry_count=%0d timeout_flag=%0d",
                 $time, state_out, error_code_out, retry_count_out, timeout_flag);

        #20;
        trigger = 1;

        #20;
        trigger = 0;
        $display("[%0t] Trigger fired.  state=%0d (expect CAMERA_CAPTURE=2)",
                 $time, state_out);

        #40;
        capture_done = 1;

        #20;
        capture_done = 0;
        $display("[%0t] Capture done.   state=%0d (expect READ_FIFO=3)",
                 $time, state_out);

        #40;
        fifo_read_done = 1;

        #20;
        fifo_read_done = 0;
        $display("[%0t] FIFO read done. state=%0d (expect ISP_PROCESS=4)",
                 $time, state_out);

        #40;
        isp_done = 1;

        #20;
        isp_done = 0;
        $display("[%0t] ISP done.       state=%0d (expect DISPLAY=5)",
                 $time, state_out);

        #40;
        display_done = 1;

        #20;
        display_done = 0;
        $display("[%0t] Display done.   state=%0d (expect WAIT_TRIGGER=1)",
                 $time, state_out);

        #20;
        $display("[%0t] END happy path: error_code=%0d retry_count=%0d timeout_flag=%0d",
                 $time, error_code_out, retry_count_out, timeout_flag);

        // -------------------------------------------------------
        // TEST: Handshake — trigger ignored when capture_ready=0
        // -------------------------------------------------------
        $display("[%0t] --- Handshake test: trigger with capture_ready=0 ---", $time);
        #20;
        rst_n = 0; #20; rst_n = 1;  // Reset back to IDLE -> WAIT_TRIGGER
        #20;

        capture_ready = 0;  // camera not ready
        trigger = 1;
        #40;                // give it several cycles
        if (state_out !== 3'd1)
            $display("FAIL handshake: expected WAIT_TRIGGER(1), got state=%0d", state_out);
        else
            $display("PASS handshake: FSM held in WAIT_TRIGGER while capture_ready=0");

        capture_ready = 1;  // now camera is ready
        #20;
        trigger = 0;
        #10;
        if (state_out !== 3'd2)
            $display("FAIL handshake: expected CAMERA_CAPTURE(2) after capture_ready=1, got state=%0d", state_out);
        else
            $display("PASS handshake: FSM advanced to CAMERA_CAPTURE once capture_ready=1");

        // -------------------------------------------------------
        // TEST: Timeout in CAMERA_CAPTURE
        // capture_done never arrives — FSM should timeout to ERROR
        // -------------------------------------------------------
        $display("[%0t] --- Timeout test: no capture_done, wait for timeout ---", $time);
        #20;
        rst_n = 0; #20; rst_n = 1;  // reset
        // Clear latches for this test (non-blocking so they sync on next clock)
        error_seen   = 0;
        timeout_seen = 0;
        capture_ready = 1;
        #20;
        trigger = 1; #10; trigger = 0;  // advance to CAMERA_CAPTURE

        // Wait well past TIMEOUT_LIMIT (10 cycles x 10ns/cycle = 100ns) plus recovery
        #200;

        if (!error_seen)
            $display("FAIL timeout: FSM never reached ERROR state");
        else
            $display("PASS timeout: FSM entered ERROR state after timeout");

        if (!timeout_seen)
            $display("FAIL timeout: timeout_flag never went high");
        else
            $display("PASS timeout: timeout_flag went high");

        if (error_code_out !== 3'd5)
            $display("FAIL timeout: expected error_code=ERR_TIMEOUT(5), got %0d", error_code_out);
        else
            $display("PASS timeout: error_code correctly shows ERR_TIMEOUT(5)");

        // -------------------------------------------------------
        // TEST: error_flag in READ_FIFO — check error_code=ERR_FIFO
        // -------------------------------------------------------
        $display("[%0t] --- Error code test: error_flag in READ_FIFO ---", $time);
        #20;
        rst_n = 0; #20; rst_n = 1;
        error_seen   = 0;
        timeout_seen = 0;
        capture_ready = 1; isp_ready = 1; display_ready = 1;
        #20;
        trigger = 1; #10; trigger = 0;   // -> CAMERA_CAPTURE
        #10;
        capture_done = 1; #10; capture_done = 0;  // -> READ_FIFO
        #10;
        error_flag = 1; #10; error_flag = 0;      // trigger error in READ_FIFO
        #30;

        if (!error_seen)
            $display("FAIL error_code: FSM never reached ERROR");
        else
            $display("PASS error_code: FSM entered ERROR");

        if (error_code_out !== 3'd2)
            $display("FAIL error_code: expected ERR_FIFO(2), got %0d", error_code_out);
        else
            $display("PASS error_code: error_code correctly shows ERR_FIFO(2)");

        // -------------------------------------------------------
        // TEST: Retry exhaustion — MAX_RETRIES=2, so 3rd error should lock
        // -------------------------------------------------------
        $display("[%0t] --- Retry exhaustion test: MAX_RETRIES=2 ---", $time);
        #20;
        rst_n = 0; #20; rst_n = 1;
        error_seen   = 0;
        timeout_seen = 0;
        capture_ready = 1;

        // Hold trigger high so every time the FSM returns to WAIT_TRIGGER it immediately
        // fires the next attempt without needing a new trigger pulse.
        // With TIMEOUT_LIMIT=10: each attempt takes ~13 cycles = 130ns
        // 3 attempts = ~390ns. Wait 600ns to be safe.
        #20;
        trigger = 1;   // keep high; FSM auto-retriggers on each WAIT_TRIGGER entry
        #600;          // wait for 3 full timeout+retry cycles
        trigger = 0;

        if (retry_count_out !== 2'd2)
            $display("INFO retry: retry_count=%0d (may still be cycling)", retry_count_out);

        if (state_out !== 3'd6)
            $display("FAIL retry: expected fatal ERROR(6), got state=%0d", state_out);
        else
            $display("PASS retry: FSM locked in ERROR after exhausting retries");

        #80;

        $finish;
    end

endmodule

sim/main_fsm.vcd
$date
	Sun May 31 17:27:31 2026
$end
$version
	Icarus Verilog
$end
$timescale
	1ps
$end
$scope module main_fsm_tb $end
$var wire 1 ! timeout_flag $end
$var wire 3 " state_out [2:0] $end
$var wire 2 # retry_count_out [1:0] $end
$var wire 1 $ isp_enable $end
$var wire 1 % fifo_read_enable $end
$var wire 3 & error_code_out [2:0] $end
$var wire 1 ' display_enable $end
$var wire 1 ( camera_enable $end
$var reg 1 ) capture_done $end
$var reg 1 * capture_ready $end
$var reg 1 + clk $end
$var reg 1 , display_done $end
$var reg 1 - display_ready $end
$var reg 1 . error_flag $end
$var reg 1 / error_seen $end
$var reg 1 0 fifo_read_done $end
$var reg 1 1 isp_done $end
$var reg 1 2 isp_ready $end
$var reg 1 3 rst_n $end
$var reg 1 4 timeout_seen $end
$var reg 1 5 trigger $end
$scope module uut $end
$var wire 1 ) capture_done $end
$var wire 1 * capture_ready $end
$var wire 1 + clk $end
$var wire 1 , display_done $end
$var wire 1 - display_ready $end
$var wire 3 6 error_code_out [2:0] $end
$var wire 1 . error_flag $end
$var wire 1 0 fifo_read_done $end
$var wire 1 1 isp_done $end
$var wire 1 2 isp_ready $end
$var wire 2 7 retry_count_out [1:0] $end
$var wire 1 3 rst_n $end
$var wire 3 8 state_out [2:0] $end
$var wire 1 ! timeout_flag $end
$var wire 1 5 trigger $end
$var wire 1 9 timeout_hit $end
$var parameter 3 : CAMERA_CAPTURE $end
$var parameter 3 ; DISPLAY $end
$var parameter 3 < ERROR $end
$var parameter 3 = ERR_CAPTURE $end
$var parameter 3 > ERR_DISPLAY $end
$var parameter 3 ? ERR_FIFO $end
$var parameter 3 @ ERR_ISP $end
$var parameter 3 A ERR_NONE $end
$var parameter 3 B ERR_TIMEOUT $end
$var parameter 3 C IDLE $end
$var parameter 3 D ISP_PROCESS $end
$var parameter 2 E MAX_RETRIES $end
$var parameter 3 F READ_FIFO $end
$var parameter 8 G TIMEOUT_LIMIT $end
$var parameter 3 H WAIT_TRIGGER $end
$var reg 1 ( camera_enable $end
$var reg 1 ' display_enable $end
$var reg 3 I error_code [2:0] $end
$var reg 1 % fifo_read_enable $end
$var reg 1 $ isp_enable $end
$var reg 3 J next_state [2:0] $end
$var reg 2 K retry_count [1:0] $end
$var reg 3 L state [2:0] $end
$var reg 8 M timeout_counter [7:0] $end
$upscope $end
$upscope $end
$enddefinitions $end
$comment Show the parameter values. $end
$dumpall
b1 H
b1010 G
b11 F
b10 E
b100 D
b0 C
b101 B
b0 A
b11 @
b10 ?
b100 >
b1 =
b110 <
b101 ;
b10 :
$end
#0
$dumpvars
b0 M
b0 L
b0 K
b1 J
b0 I
09
b0 8
b0 7
b0 6
05
04
03
12
01
00
0/
0.
1-
0,
0+
1*
0)
0(
0'
b0 &
0%
0$
b0 #
b0 "
0!
$end
#5000
1+
#10000
0+
#15000
1+
#20000
0+
13
#25000
b1 "
b1 8
b1 L
1+
#30000
0+
#35000
b1 M
1+
#40000
b10 J
0+
15
#45000
1(
b0 M
b10 "
b10 8
b10 L
1+
#50000
0+
#55000
b1 M
1+
#60000
0+
05
#65000
b10 M
1+
#70000
0+
#75000
b11 M
1+
#80000
0+
#85000
b100 M
1+
#90000
0+
#95000
b101 M
1+
#100000
b11 J
0+
1)
#105000
1%
0(
b0 M
b11 "
b11 8
b11 L
1+
#110000
0+
#115000
b1 M
1+
#120000
0+
0)
#125000
b10 M
1+
#130000
0+
#135000
b11 M
1+
#140000
0+
#145000
b100 M
1+
#150000
0+
#155000
b101 M
1+
#160000
b100 J
0+
10
#165000
1$
0%
b0 M
b100 "
b100 8
b100 L
1+
#170000
0+
#175000
b1 M
1+
#180000
0+
00
#185000
b10 M
1+
#190000
0+
#195000
b11 M
1+
#200000
0+
#205000
b100 M
1+
#210000
0+
#215000
b101 M
1+
#220000
b101 J
0+
11
#225000
1'
0$
b0 M
b101 "
b101 8
b101 L
1+
#230000
0+
#235000
b1 M
1+
#240000
0+
01
#245000
b10 M
1+
#250000
0+
#255000
b11 M
1+
#260000
0+
#265000
b100 M
1+
#270000
0+
#275000
b101 M
1+
#280000
b1 J
0+
1,
#285000
0'
b0 M
b1 "
b1 8
b1 L
1+
#290000
0+
#295000
b1 M
1+
#300000
0+
0,
#305000
b10 M
1+
#310000
0+
#315000
b11 M
1+
#320000
0+
#325000
b100 M
1+
#330000
0+
#335000
b101 M
1+
#340000
b1 J
b0 M
b0 "
b0 8
b0 L
0+
03
#345000
1+
#350000
0+
#355000
1+
#360000
0+
13
#365000
b1 "
b1 8
b1 L
1+
#370000
0+
#375000
b1 M
1+
#380000
0+
15
0*
#385000
b10 M
1+
#390000
0+
#395000
b11 M
1+
#400000
0+
#405000
b100 M
1+
#410000
0+
#415000
b101 M
1+
#420000
b10 J
0+
1*
#425000
1(
b10 "
b10 8
b10 L
b0 M
1+
#430000
0+
#435000
b1 M
1+
#440000
0+
05
#445000
b10 M
1+
#450000
0+
#455000
b11 M
1+
#460000
0+
#465000
b100 M
1+
#470000
0(
b1 J
b0 M
b0 "
b0 8
b0 L
0+
03
#475000
1+
#480000
0+
#485000
1+
#490000
0+
13
#495000
b1 "
b1 8
b1 L
1+
#500000
0+
#505000
b1 M
1+
#510000
b10 J
0+
15
#515000
1(
b10 "
b10 8
b10 L
b0 M
1+
#520000
0+
05
#525000
b1 M
1+
#530000
0+
#535000
b10 M
1+
#540000
0+
#545000
b11 M
1+
#550000
0+
#555000
b100 M
1+
#560000
0+
#565000
b101 M
1+
#570000
0+
#575000
b110 M
1+
#580000
0+
#585000
b111 M
1+
#590000
0+
#595000
b1000 M
1+
#600000
0+
#605000
b1001 M
1+
#610000
0+
#615000
b110 J
1!
19
b1010 M
1+
#620000
0+
#625000
0(
b1 J
0!
09
b0 M
b101 &
b101 6
b101 I
b110 "
b110 8
b110 L
14
1+
#630000
0+
#635000
b1 #
b1 7
b1 K
b1 "
b1 8
b1 L
1/
1+
#640000
0+
#645000
b1 M
1+
#650000
0+
#655000
b10 M
1+
#660000
0+
#665000
b11 M
1+
#670000
0+
#675000
b100 M
1+
#680000
0+
#685000
b101 M
1+
#690000
0+
#695000
b110 M
1+
#700000
0+
#705000
b111 M
1+
#710000
0+
#715000
b1000 M
1+
#720000
0+
#725000
b1001 M
1+
#730000
0+
#735000
1!
19
b1010 M
1+
#740000
b1 J
0!
09
b0 M
b0 #
b0 7
b0 K
b0 &
b0 6
b0 I
b0 "
b0 8
b0 L
0+
03
#745000
1+
#750000
0+
#755000
1+
#760000
0+
04
0/
13
#765000
b1 "
b1 8
b1 L
1+
#770000
0+
#775000
b1 M
1+
#780000
b10 J
0+
15
#785000
1(
b10 "
b10 8
b10 L
b0 M
1+
#790000
0+
05
#795000
b1 M
1+
#800000
b11 J
0+
1)
#805000
1%
0(
b11 "
b11 8
b11 L
b0 M
1+
#810000
0+
0)
#815000
b1 M
1+
#820000
b110 J
0+
1.
#825000
0%
b1 J
b10 &
b10 6
b10 I
b110 "
b110 8
b110 L
b0 M
1+
#830000
b1 J
0+
0.
#835000
b1 #
b1 7
b1 K
b1 "
b1 8
b1 L
1/
1+
#840000
0+
#845000
b1 M
1+
#850000
0+
#855000
b10 M
1+
#860000
0+
#865000
b11 M
1+
#870000
0+
#875000
b100 M
1+
#880000
b1 J
b0 #
b0 7
b0 K
b0 &
b0 6
b0 I
b0 "
b0 8
b0 L
b0 M
0+
03
#885000
1+
#890000
0+
#895000
1+
#900000
0+
0/
13
#905000
b1 "
b1 8
b1 L
1+
#910000
0+
#915000
b1 M
1+
#920000
b10 J
0+
15
#925000
1(
b0 M
b10 "
b10 8
b10 L
1+
#930000
0+
#935000
b1 M
1+
#940000
0+
#945000
b10 M
1+
#950000
0+
#955000
b11 M
1+
#960000
0+
#965000
b100 M
1+
#970000
0+
#975000
b101 M
1+
#980000
0+
#985000
b110 M
1+
#990000
0+
#995000
b111 M
1+
#1000000
0+
#1005000
b1000 M
1+
#1010000
0+
#1015000
b1001 M
1+
#1020000
0+
#1025000
b110 J
1!
19
b1010 M
1+
#1030000
0+
#1035000
0(
b1 J
b101 &
b101 6
b101 I
b110 "
b110 8
b110 L
0!
09
b0 M
14
1+
#1040000
0+
#1045000
b10 J
b1 #
b1 7
b1 K
b1 "
b1 8
b1 L
1/
1+
#1050000
0+
#1055000
1(
b10 "
b10 8
b10 L
1+
#1060000
0+
#1065000
b1 M
1+
#1070000
0+
#1075000
b10 M
1+
#1080000
0+
#1085000
b11 M
1+
#1090000
0+
#1095000
b100 M
1+
#1100000
0+
#1105000
b101 M
1+
#1110000
0+
#1115000
b110 M
1+
#1120000
0+
#1125000
b111 M
1+
#1130000
0+
#1135000
b1000 M
1+
#1140000
0+
#1145000
b1001 M
1+
#1150000
0+
#1155000
b110 J
1!
19
b1010 M
1+
#1160000
0+
#1165000
0(
b1 J
0!
09
b0 M
b110 "
b110 8
b110 L
1+
#1170000
0+
#1175000
b10 J
b10 #
b10 7
b10 K
b1 "
b1 8
b1 L
1+
#1180000
0+
#1185000
1(
b10 "
b10 8
b10 L
1+
#1190000
0+
#1195000
b1 M
1+
#1200000
0+
#1205000
b10 M
1+
#1210000
0+
#1215000
b11 M
1+
#1220000
0+
#1225000
b100 M
1+
#1230000
0+
#1235000
b101 M
1+
#1240000
0+
#1245000
b110 M
1+
#1250000
0+
#1255000
b111 M
1+
#1260000
0+
#1265000
b1000 M
1+
#1270000
0+
#1275000
b1001 M
1+
#1280000
0+
#1285000
b110 J
1!
19
b1010 M
1+
#1290000
0+
#1295000
0(
b110 "
b110 8
b110 L
0!
09
b0 M
1+
#1300000
0+
#1305000
b1 M
1+
#1310000
0+
#1315000
b10 M
1+
#1320000
0+
#1325000
b11 M
1+
#1330000
0+
#1335000
b100 M
1+
#1340000
0+
#1345000
b101 M
1+
#1350000
0+
#1355000
b110 M
1+
#1360000
0+
#1365000
b111 M
1+
#1370000
0+
#1375000
b1000 M
1+
#1380000
0+
#1385000
b1001 M
1+
#1390000
0+
#1395000
1!
19
b1010 M
1+
#1400000
0+
#1405000
1+
#1410000
0+
#1415000
1+
#1420000
0+
#1425000
1+
#1430000
0+
#1435000
1+
#1440000
0+
#1445000
1+
#1450000
0+
#1455000
1+
#1460000
0+
#1465000
1+
#1470000
0+
#1475000
1+
#1480000
0+
#1485000
1+
#1490000
0+
#1495000
1+
#1500000
0+
#1505000
1+
#1510000
0+
#1515000
1+
#1520000
0+
05
