rtl/ov7670_capture.v
// ov7670_capture.v
// Captures raw 8-bit Bayer pixels from the OV7670 camera sensor.
// All logic runs in the pclk (pixel clock) domain (~24 MHz on hardware).
//
// OV7670 Signal Reference:
//   pclk      - Pixel clock from camera. Every rising edge delivers one byte of data.
//   vsync     - Vertical sync. HIGH during the blanking gap BETWEEN frames.
//               LOW while a frame is actively being transmitted.
//   href      - Horizontal reference. HIGH while a row of pixels is being sent.
//               LOW during horizontal blanking between rows.
//   cam_data  - Raw 8-bit Bayer byte from the camera. Valid on each pclk when href is HIGH.

module ov7670_capture (
    input  wire       pclk,        // Pixel clock from OV7670 (~24 MHz)
    input  wire       rst_n,       // Active-low asynchronous reset
    input  wire       vsync,       // Vertical sync (HIGH = blanking, LOW = active frame)
    input  wire       href,        // Horizontal reference (HIGH = active row)
    input  wire [7:0] cam_data,    // Raw Bayer pixel byte from camera
    output reg  [7:0] pixel_data,  // Captured pixel byte (holds last value when invalid)
    output reg        pixel_valid, // HIGH for one pclk cycle per valid pixel byte
    output reg        frame_valid, // HIGH while a frame is actively being sent
    output reg        line_valid   // HIGH while a row of pixels is being sent
);

    // All outputs are registered on posedge pclk.
    // Registering outputs removes glitches and ensures clean, synchronous
    // transitions that downstream modules can safely sample.
    //
    // Async reset (negedge rst_n) brings all outputs to a known safe state
    // without waiting for a clock edge — useful during power-up.

    always @(posedge pclk or negedge rst_n) begin
        if (!rst_n) begin
            // Reset all outputs to 0 (safe/inactive state)
            pixel_data  <= 8'h00;
            pixel_valid <= 1'b0;
            frame_valid <= 1'b0;
            line_valid  <= 1'b0;
        end else begin
            // vsync is HIGH during blanking (no frame), LOW during active frame.
            // We invert it so frame_valid=1 means "a frame is in progress" —
            // a more intuitive polarity for downstream logic.
            frame_valid <= ~vsync;

            // line_valid directly follows href: HIGH when a row is being sent.
            line_valid  <= href;

            if (href) begin
                // Camera is sending valid pixel data this clock cycle.
                // Latch the byte and assert pixel_valid for exactly one cycle.
                pixel_data  <= cam_data;
                pixel_valid <= 1'b1;
            end else begin
                // No active row — deassert pixel_valid.
                // pixel_data retains its last value (don't-care but harmless).
                pixel_valid <= 1'b0;
            end
        end
    end

endmodule

tb/ov7670_capture_tb.v
`timescale 1ns / 1ps
// ov7670_capture_tb.v
// Testbench for ov7670_capture module.
// Simulates a mini two-row camera frame to verify pixel capture behavior.

module ov7670_capture_tb;

    // ---------------------------------------------------------------------------
    // DUT signals
    // ---------------------------------------------------------------------------
    reg        pclk;
    reg        rst_n;
    reg        vsync;
    reg        href;
    reg  [7:0] cam_data;

    wire [7:0] pixel_data;
    wire       pixel_valid;
    wire       frame_valid;
    wire       line_valid;

    // ---------------------------------------------------------------------------
    // Instantiate the Device Under Test
    // ---------------------------------------------------------------------------
    ov7670_capture dut (
        .pclk       (pclk),
        .rst_n      (rst_n),
        .vsync      (vsync),
        .href       (href),
        .cam_data   (cam_data),
        .pixel_data (pixel_data),
        .pixel_valid(pixel_valid),
        .frame_valid(frame_valid),
        .line_valid (line_valid)
    );

    // ---------------------------------------------------------------------------
    // Clock: 10 ns period (~100 MHz in sim; real camera uses ~24 MHz pclk)
    // ---------------------------------------------------------------------------
    initial pclk = 0;
    always #5 pclk = ~pclk;

    // ---------------------------------------------------------------------------
    // VCD waveform dump (viewed in GTKWave)
    // ---------------------------------------------------------------------------
    initial begin
        $dumpfile("sim/ov7670_capture.vcd");
        $dumpvars(0, ov7670_capture_tb);
    end

    // ---------------------------------------------------------------------------
    // Event latches — because outputs are registered, transitions appear ONE
    // clock cycle after the input changes.  We use latching always-blocks so
    // we don't miss a transient assertion during the sequential stimulus.
    // ---------------------------------------------------------------------------
    reg pixel_valid_seen;  // Goes 1 the first time pixel_valid is observed HIGH
    reg frame_went_high;   // Goes 1 the first time frame_valid is observed HIGH

    initial begin
        pixel_valid_seen = 0;
        frame_went_high  = 0;
    end

    always @(posedge pclk) begin
        if (pixel_valid)  pixel_valid_seen <= 1;
        if (frame_valid)  frame_went_high  <= 1;
    end

    // ---------------------------------------------------------------------------
    // Display every captured pixel as it appears
    // ---------------------------------------------------------------------------
    always @(posedge pclk) begin
        if (pixel_valid)
            $display("  [pclk] pixel_valid=1  pixel_data=0x%02h  frame_valid=%b  line_valid=%b",
                     pixel_data, frame_valid, line_valid);
    end

    // ---------------------------------------------------------------------------
    // Main stimulus
    // ---------------------------------------------------------------------------
    integer pixel_count;

    initial begin
        // 1. Initialize all inputs to safe/inactive state
        pclk        = 0;
        rst_n       = 0;   // Hold in reset
        vsync       = 1;   // Camera in vertical blanking
        href        = 0;   // No active row
        cam_data    = 8'h00;
        pixel_count = 0;

        $display("=== OV7670 Capture Testbench Start ===");

        // 2. Release reset after 20 ns
        #20;
        rst_n = 1;
        $display("[%0t ns] Reset released (rst_n=1)", $time);

        // 3. Stay in vertical blanking for 40 ns
        #40;
        vsync = 1;
        $display("[%0t ns] vsync=1 (vertical blanking)", $time);

        // 4. Begin active frame (vsync LOW)
        vsync = 0;
        #10;
        $display("[%0t ns] vsync=0  -> frame_valid should go HIGH next cycle", $time);

        // ------------------------------------------------------------------
        // 5. Row 1: 4 Bayer bytes  0xA0 0xA1 0xA2 0xA3
        // ------------------------------------------------------------------
        $display("[%0t ns] --- Row 1 start (href=1) ---", $time);
        href = 1;

        cam_data = 8'hA0; #10;
        cam_data = 8'hA1; #10;
        cam_data = 8'hA2; #10;
        cam_data = 8'hA3; #10;

        href = 0;
        $display("[%0t ns] --- Row 1 end   (href=0) ---", $time);
        #20;

        // ------------------------------------------------------------------
        // 6. Row 2: 4 Bayer bytes  0xB0 0xB1 0xB2 0xB3
        // ------------------------------------------------------------------
        $display("[%0t ns] --- Row 2 start (href=1) ---", $time);
        href = 1;

        cam_data = 8'hB0; #10;
        cam_data = 8'hB1; #10;
        cam_data = 8'hB2; #10;
        cam_data = 8'hB3; #10;

        href = 0;
        $display("[%0t ns] --- Row 2 end   (href=0) ---", $time);
        #20;

        // 7. End of frame — vsync goes HIGH again (vertical blanking)
        vsync = 1;
        $display("[%0t ns] vsync=1  -> frame_valid should go LOW next cycle", $time);
        #40;

        // ------------------------------------------------------------------
        // 8. Results — wait one extra cycle so registered outputs have settled
        // ------------------------------------------------------------------
        @(posedge pclk); // let the last vsync=1 propagate through registers
        #1;              // tiny delta to read stable wire values

        $display("");
        $display("=== Simulation Results ===");

        // Check: frame_valid went HIGH during the active frame
        if (frame_went_high)
            $display("PASS: frame_valid went HIGH (frame was detected)");
        else
            $display("FAIL: frame_valid never went HIGH");

        // Check: pixel_valid went HIGH during href rows
        if (pixel_valid_seen)
            $display("PASS: pixel_valid went HIGH (pixels were captured)");
        else
            $display("FAIL: pixel_valid never went HIGH");

        // Check: frame_valid is LOW now that vsync=1 again
        if (!frame_valid)
            $display("PASS: frame_valid is LOW at end of frame (vsync=1)");
        else
            $display("FAIL: frame_valid is still HIGH at end of frame");

        $display("=== Testbench Complete ===");
        $finish;
    end

endmodule

sim/ov7670_capture.vcd
$date
	Tue Jun 02 14:14:12 2026
$end
$version
	Icarus Verilog
$end
$timescale
	1ps
$end
$scope module ov7670_capture_tb $end
$var wire 1 ! pixel_valid $end
$var wire 8 " pixel_data [7:0] $end
$var wire 1 # line_valid $end
$var wire 1 $ frame_valid $end
$var reg 8 % cam_data [7:0] $end
$var reg 1 & frame_went_high $end
$var reg 1 ' href $end
$var reg 1 ( pclk $end
$var reg 1 ) pixel_valid_seen $end
$var reg 1 * rst_n $end
$var reg 1 + vsync $end
$var integer 32 , pixel_count [31:0] $end
$scope module dut $end
$var wire 8 - cam_data [7:0] $end
$var wire 1 ' href $end
$var wire 1 ( pclk $end
$var wire 1 * rst_n $end
$var wire 1 + vsync $end
$var reg 1 $ frame_valid $end
$var reg 1 # line_valid $end
$var reg 8 . pixel_data [7:0] $end
$var reg 1 ! pixel_valid $end
$upscope $end
$upscope $end
$enddefinitions $end
$comment Show the parameter values. $end
$dumpall
$end
#0
$dumpvars
b0 .
b0 -
b0 ,
1+
0*
0)
0(
0'
0&
b0 %
0$
0#
b0 "
0!
$end
#5000
1(
#10000
0(
#15000
1(
#20000
0(
1*
#25000
1(
#30000
0(
#35000
1(
#40000
0(
#45000
1(
#50000
0(
#55000
1(
#60000
0(
0+
#65000
1$
1(
#70000
0(
b10100000 %
b10100000 -
1'
#75000
1!
b10100000 "
b10100000 .
1#
1&
1(
#80000
0(
b10100001 %
b10100001 -
#85000
b10100001 "
b10100001 .
1)
1(
#90000
0(
b10100010 %
b10100010 -
#95000
b10100010 "
b10100010 .
1(
#100000
0(
b10100011 %
b10100011 -
#105000
b10100011 "
b10100011 .
1(
#110000
0(
0'
#115000
0!
0#
1(
#120000
0(
#125000
1(
#130000
0(
b10110000 %
b10110000 -
1'
#135000
1!
b10110000 "
b10110000 .
1#
1(
#140000
0(
b10110001 %
b10110001 -
#145000
b10110001 "
b10110001 .
1(
#150000
0(
b10110010 %
b10110010 -
#155000
b10110010 "
b10110010 .
1(
#160000
0(
b10110011 %
b10110011 -
#165000
b10110011 "
b10110011 .
1(
#170000
0(
0'
#175000
0!
0#
1(
#180000
0(
#185000
1(
#190000
0(
1+
#195000
0$
1(
